{
  "topic": "#何小鹏首次披露物理AI巨大进展#",
  "fetched_at": "2025-11-05T15:44:41+08:00",
  "total": 20,
  "top_n": 30,
  "items": [
    {
      "id": "detail-5099236903767875351",
      "bid": null,
      "url": "https://weibo.com/3175087234/Qcr341B51?refer_flag=1001030103_",
      "created_at": "34分钟前",
      "user_id": null,
      "user_name": "梁一鸣Max",
      "verified": null,
      "region": null,
      "source": "",
      "text": "#小鹏科技日#来了，#何小鹏首次披露物理AI巨大进展#？！开场一直在说物理AI，何小鹏总说今天发布会很硬核，会是啥？2广州·广州小鹏科技园-T2北门​",
      "text_raw": "#小鹏科技日#来了，#何小鹏首次披露物理AI巨大进展#？！开场一直在说物理AI，何小鹏总说今天发布会很硬核，会是啥？2广州·广州小鹏科技园-T2北门​",
      "reposts": 4,
      "comments": 131,
      "likes": 124,
      "pics": [
        "https://tvax4.sinaimg.cn/crop.0.0.750.750.180/0085KfK1ly8h540v278acj30ku0kuzkp.jpg?KID=imgbed,tva&Expires=1762339474&ssig=0KqL36UxNX",
        "https://tva3.sinaimg.cn/crop.106.24.313.313.180/bd3ffc82gw1e8jk24rip0j20ei0d0tan.jpg?KID=imgbed,tva&Expires=1762339475&ssig=MA%2FCQChNnQ",
        "https://h5.sinaimg.cn/upload/108/1866/2022/11/02/vvip_2.png",
        "https://wx1.sinaimg.cn/orj360/bd3ffc82gy1i71crlbwkaj21400u0tdo.jpg",
        "https://wx2.sinaimg.cn/orj360/bd3ffc82gy1i71cs8r1grj21400u0dm8.jpg",
        "https://wx2.sinaimg.cn/orj360/bd3ffc82gy1i71cs4n53dj21400u0ag9.jpg",
        "https://wx4.sinaimg.cn/orj360/bd3ffc82gy1i71cujb3ruj20u013xjuj.jpg",
        "https://wx1.sinaimg.cn/orj360/bd3ffc82gy1i71cruzn34j21400u00zx.jpg",
        "https://tva1.sinaimg.cn/default/images/default_avatar_male_180.gif",
        "https://a.sinaimg.cn/mintra/pic/2201190827/32aria.png"
      ],
      "video": {
        "title": null,
        "cover": null,
        "duration": null,
        "streams": {
          "stream_url": "https://livephoto.us.sinaimg.cn/000U7Oehjx08sJU5TSxh0h04110055CI0k01.mov?Expires=1762332275&ssig=UQcrWrp0rX&KID=unistore,video"
        }
      },
      "score": 54.099999999999994
    },
    {
      "id": "detail-796662870135250115",
      "bid": null,
      "url": "https://weibo.com/3175087234/QcqHfwesH?refer_flag=1001030103_",
      "created_at": "今天14:16",
      "user_id": null,
      "user_name": "梁一鸣Max",
      "verified": null,
      "region": null,
      "source": "",
      "text": "#小鹏科技日#给你们看看全新营销部门办公室。加班累了，除了可以看看自己热搜上榜了没，还可以看看@XP-何小鹏的Q版照片提提神#何小鹏首次披露物理AI巨大进展#​​​",
      "text_raw": "#小鹏科技日#给你们看看全新营销部门办公室。加班累了，除了可以看看自己热搜上榜了没，还可以看看@XP-何小鹏的Q版照片提提神#何小鹏首次披露物理AI巨大进展#​​​",
      "reposts": 6,
      "comments": 126,
      "likes": 127,
      "pics": [
        "https://tvax4.sinaimg.cn/crop.0.0.750.750.180/0085KfK1ly8h540v278acj30ku0kuzkp.jpg?KID=imgbed,tva&Expires=1762339474&ssig=0KqL36UxNX",
        "https://tva3.sinaimg.cn/crop.106.24.313.313.180/bd3ffc82gw1e8jk24rip0j20ei0d0tan.jpg?KID=imgbed,tva&Expires=1762339476&ssig=57ylbTyUnN",
        "https://h5.sinaimg.cn/upload/108/1866/2022/11/02/vvip_2.png",
        "https://wx2.sinaimg.cn/orj360/bd3ffc82gy1i71b8ni9qyj213x0u078b.jpg",
        "https://wx1.sinaimg.cn/orj360/bd3ffc82gy1i71b8s0ktpj21400u0tde.jpg",
        "https://wx1.sinaimg.cn/orj360/bd3ffc82gy1i71b91vb3aj21400u0ahf.jpg",
        "https://wx1.sinaimg.cn/orj360/bd3ffc82gy1i71b8ywbegj21400u0n2i.jpg",
        "https://wx2.sinaimg.cn/orj360/bd3ffc82gy1i71b94xbt5j20u0140qaq.jpg",
        "https://ww1.sinaimg.cn/mw690/549d0121tw1egm1kjly3jj20hs0hsq4f.jpg",
        "https://a.sinaimg.cn/mintra/pic/2201190827/32aria.png"
      ],
      "video": {
        "title": null,
        "cover": null,
        "duration": null,
        "streams": {
          "stream_url": "https://livephoto.us.sinaimg.cn/002R7ZOIjx08sJUZ7dY40h0411002hAZ0k01.mov?Expires=1762332276&ssig=SLrEJ45Y2A&KID=unistore,video"
        }
      },
      "score": 54.1
    },
    {
      "id": "detail-5962857400774495986",
      "bid": null,
      "url": "https://weibo.com/3175087234/QcrcXzAz3?refer_flag=1001030103_",
      "created_at": "10分钟前",
      "user_id": null,
      "user_name": "梁一鸣Max",
      "verified": null,
      "region": null,
      "source": "",
      "text": "#小鹏科技日#上，小鹏公布了第二代VLA。VLA指的是从视觉Vision到语言Language，再到行动Action。这当中翻译成语言是AI驾驶中必不可少的一部分。小鹏这次公布的第二代VLA，通过大幅缩减Language，也就是语言部分。直接转化成Action。搭载第二代VLA系统的小鹏智驾系统，学习能力更强了，实现复杂 ​展开c",
      "text_raw": "#小鹏科技日#上，小鹏公布了第二代VLA。VLA指的是从视觉Vision到语言Language，再到行动Action。这当中翻译成语言是AI驾驶中必不可少的一部分。小鹏这次公布的第二代VLA，通过大幅缩减Language，也就是语言部分。直接转化成Action。搭载第二代VLA系统的小鹏智驾系统，学习能力更强了，实现复杂 ​展开c",
      "reposts": 6,
      "comments": 96,
      "likes": 96,
      "pics": [
        "https://tvax4.sinaimg.cn/crop.0.0.750.750.180/0085KfK1ly8h540v278acj30ku0kuzkp.jpg?KID=imgbed,tva&Expires=1762339474&ssig=0KqL36UxNX",
        "https://tva3.sinaimg.cn/crop.106.24.313.313.180/bd3ffc82gw1e8jk24rip0j20ei0d0tan.jpg?KID=imgbed,tva&Expires=1762339475&ssig=MA%2FCQChNnQ",
        "https://h5.sinaimg.cn/upload/108/1866/2022/11/02/vvip_2.png",
        "https://wx3.sinaimg.cn/orj360/bd3ffc82gy1i71dehetufj21400u0qa0.jpg",
        "https://wx2.sinaimg.cn/orj360/bd3ffc82gy1i71delrkt2j21400u044u.jpg",
        "https://wx3.sinaimg.cn/orj360/bd3ffc82gy1i71de55ca0j21400u07bh.jpg",
        "https://wx1.sinaimg.cn/orj360/bd3ffc82gy1i71deei9pyj21400u0gqp.jpg",
        "https://wx2.sinaimg.cn/orj360/bd3ffc82gy1i71dec32gvj21400u00yx.jpg",
        "https://tva1.sinaimg.cn/default/images/default_avatar_male_180.gif",
        "https://a.sinaimg.cn/mintra/pic/2201190827/32aria.png"
      ],
      "video": {
        "title": null,
        "cover": null,
        "duration": null,
        "streams": {
          "stream_url": "https://livephoto.us.sinaimg.cn/003JakC6gx08sJVeZHXh0f0f01005N6b0k01.mov?Expires=1762332275&ssig=60KgFCP%2B61&KID=unistore,video"
        }
      },
      "score": 42.0
    },
    {
      "id": "detail-4644324604926777957",
      "bid": null,
      "url": "https://weibo.com/3175087234/QcqYa1eRo?refer_flag=1001030103_",
      "created_at": "46分钟前",
      "user_id": null,
      "user_name": "梁一鸣Max",
      "verified": null,
      "region": null,
      "source": "",
      "text": "小鹏是一家很包容的公司。今天各大友商都有人来庆祝#小鹏科技日#。比如有穿这种衣服的。开这种车的，还有用这种手机的统统都欢迎#何小鹏首次披露物理AI巨大进展#2广州·广州小鹏科技园-T2北门​",
      "text_raw": "小鹏是一家很包容的公司。今天各大友商都有人来庆祝#小鹏科技日#。比如有穿这种衣服的。开这种车的，还有用这种手机的统统都欢迎#何小鹏首次披露物理AI巨大进展#2广州·广州小鹏科技园-T2北门​",
      "reposts": 2,
      "comments": 106,
      "likes": 104,
      "pics": [
        "https://tvax4.sinaimg.cn/crop.0.0.750.750.180/0085KfK1ly8h540v278acj30ku0kuzkp.jpg?KID=imgbed,tva&Expires=1762339474&ssig=0KqL36UxNX",
        "https://tva3.sinaimg.cn/crop.106.24.313.313.180/bd3ffc82gw1e8jk24rip0j20ei0d0tan.jpg?KID=imgbed,tva&Expires=1762339475&ssig=MA%2FCQChNnQ",
        "https://h5.sinaimg.cn/upload/108/1866/2022/11/02/vvip_2.png",
        "https://wx3.sinaimg.cn/orj360/bd3ffc82gy1i71chgw093j21400u0dnp.jpg",
        "https://wx2.sinaimg.cn/orj360/bd3ffc82gy1i71carxpy5j20v00n9761.jpg",
        "https://ww1.sinaimg.cn/mw690/549d0121tw1egm1kjly3jj20hs0hsq4f.jpg",
        "https://a.sinaimg.cn/mintra/pic/2201190827/32aria.png"
      ],
      "video": {
        "title": null,
        "cover": null,
        "duration": null,
        "streams": {
          "stream_url": "https://livephoto.us.sinaimg.cn/003TUrVKjx08sJUV67a70h041100529s0k01.mov?Expires=1762332275&ssig=Ap4IZMTOrI&KID=unistore,video"
        }
      },
      "score": 43.4
    },
    {
      "id": "detail-2369640330930866270",
      "bid": null,
      "url": "https://weibo.com/6244484654/Qcr6TDae4?refer_flag=1001030103_",
      "created_at": "24分钟前",
      "user_id": null,
      "user_name": "互联网三爷",
      "verified": null,
      "region": null,
      "source": "",
      "text": "#何小鹏首次披露物理AI巨大进展#2025 小鹏科技日以「涌现Emergence」为题，是小鹏在过去技术积累至临界点后迎来的爆发点，更是在AI与物理世界的深度融合后，所迸发出的全新可能。不再单一去理解数字世界的AI革命和物理世界的新能源颠覆，小鹏从全栈自研的积累实践中逐步尝试跨域融合。而当AI与物理 ​展开c",
      "text_raw": "#何小鹏首次披露物理AI巨大进展#2025 小鹏科技日以「涌现Emergence」为题，是小鹏在过去技术积累至临界点后迎来的爆发点，更是在AI与物理世界的深度融合后，所迸发出的全新可能。不再单一去理解数字世界的AI革命和物理世界的新能源颠覆，小鹏从全栈自研的积累实践中逐步尝试跨域融合。而当AI与物理 ​展开c",
      "reposts": 22,
      "comments": 42,
      "likes": 194,
      "pics": [
        "https://tvax4.sinaimg.cn/crop.0.0.750.750.180/0085KfK1ly8h540v278acj30ku0kuzkp.jpg?KID=imgbed,tva&Expires=1762339475&ssig=5byGeMLn07",
        "https://tvax4.sinaimg.cn/crop.0.0.1080.1080.180/006OBdIqly8h8v5pffuxcj30u00u07al.jpg?KID=imgbed,tva&Expires=1762339476&ssig=Sa5BHvFdo%2F",
        "https://h5.sinaimg.cn/upload/108/1866/2022/11/02/vvip_2.png",
        "https://wx2.sinaimg.cn/orj360/006OBdIqly1i71d4o53koj31r80zk3zo.jpg",
        "https://wx2.sinaimg.cn/orj360/006OBdIqly1i71d4rs593j33n421rkjm.jpg",
        "https://wx2.sinaimg.cn/orj360/006OBdIqly1i71d4u840nj33n421rkjl.jpg",
        "https://wx1.sinaimg.cn/orj360/006OBdIqly1i71d4vq4n8j33n421rb29.jpg",
        "https://wx2.sinaimg.cn/orj360/006OBdIqly1i71d4x7ijdj33n421r4qp.jpg",
        "https://wx3.sinaimg.cn/orj360/006OBdIqly1i71d4z6sjwj33n421rhdu.jpg",
        "https://wx3.sinaimg.cn/orj360/006OBdIqly1i71d50g7ogj33n421re81.jpg",
        "https://wx2.sinaimg.cn/orj360/006OBdIqly1i71d5299y7j33n421rhdt.jpg",
        "https://wx1.sinaimg.cn/orj360/006OBdIqly1i71d53nji5j33n421rnpd.jpg",
        "https://wx1.sinaimg.cn/orj360/006OBdIqly1i71d553dpsj33n421rnpd.jpg",
        "https://wx4.sinaimg.cn/orj360/006OBdIqly1i71d56sf11j33n421rnpd.jpg",
        "https://tva1.sinaimg.cn/default/images/default_avatar_male_180.gif",
        "https://a.sinaimg.cn/mintra/pic/2201190827/32aria.png"
      ],
      "video": null,
      "score": 45.2
    },
    {
      "id": "detail-4284856838606895887",
      "bid": null,
      "url": "https://weibo.com/3175087234/QcqA3d2wZ?refer_flag=1001030103_",
      "created_at": "今天13:58",
      "user_id": null,
      "user_name": "梁一鸣Max",
      "verified": null,
      "region": null,
      "source": "",
      "text": "#小鹏科技日#我是谁？我在哪？这哪里像现实！？感觉就像穿越到了未来啊。跟你们说，小鹏未来将是一家买汽车送飞机的公司。噢耶不！？#何小鹏首次披露物理AI巨大进展#​​​2广州·广州小鹏科技园-T2北门​",
      "text_raw": "#小鹏科技日#我是谁？我在哪？这哪里像现实！？感觉就像穿越到了未来啊。跟你们说，小鹏未来将是一家买汽车送飞机的公司。噢耶不！？#何小鹏首次披露物理AI巨大进展#​​​2广州·广州小鹏科技园-T2北门​",
      "reposts": 14,
      "comments": 153,
      "likes": 147,
      "pics": [
        "https://tvax4.sinaimg.cn/crop.0.0.750.750.180/0085KfK1ly8h540v278acj30ku0kuzkp.jpg?KID=imgbed,tva&Expires=1762339475&ssig=5byGeMLn07",
        "https://tva3.sinaimg.cn/crop.106.24.313.313.180/bd3ffc82gw1e8jk24rip0j20ei0d0tan.jpg?KID=imgbed,tva&Expires=1762339476&ssig=57ylbTyUnN",
        "https://h5.sinaimg.cn/upload/108/1866/2022/11/02/vvip_2.png",
        "https://wx1.sinaimg.cn/orj360/bd3ffc82gy1i71apoav6hj21400u0grp.jpg",
        "https://wx2.sinaimg.cn/orj360/bd3ffc82gy1i71apsfwlzj21400u0n0g.jpg",
        "https://wx2.sinaimg.cn/orj360/bd3ffc82gy1i71apwbkvfj21400u0jvb.jpg",
        "https://wx4.sinaimg.cn/orj360/bd3ffc82gy1i71aq155p1j21400u043q.jpg",
        "https://wx1.sinaimg.cn/orj360/bd3ffc82gy1i71apz1uipj21400u078b.jpg",
        "https://ww1.sinaimg.cn/mw690/549d0121tw1egm1kjly3jj20hs0hsq4f.jpg",
        "https://tva3.sinaimg.cn/crop.106.24.313.313.180/bd3ffc82gw1e8jk24rip0j20ei0d0tan.jpg?KID=imgbed,tva&Expires=1762339477&ssig=vgq0HfjgxJ",
        "https://a.sinaimg.cn/mintra/pic/2201190827/32aria.png"
      ],
      "video": {
        "title": null,
        "cover": null,
        "duration": null,
        "streams": {
          "stream_url": "https://livephoto.us.sinaimg.cn/0047wMetjx08sJUZgCZG0h0411001P150k01.mov?Expires=1762332276&ssig=gS8f48rO5A&KID=unistore,video"
        }
      },
      "score": 69.0
    },
    {
      "id": "detail-5671412390538625686",
      "bid": null,
      "url": "https://weibo.com/3175087234/QcqoxvFhh?refer_flag=1001030103_",
      "created_at": "今天13:30",
      "user_id": null,
      "user_name": "梁一鸣Max",
      "verified": null,
      "region": null,
      "source": "",
      "text": "噢耶#小鹏科技日#，梁一鸣本鸣来了，给我发了工牌，像不像？把我整的这么温柔可惜没赶上食堂。付款时除了有价格，连卡路里等营养信息都会展示。羡慕在小鹏上班的同学们#何小鹏首次披露物理AI巨大进展#​​​2广州·广州小鹏科技园-T2北门​",
      "text_raw": "噢耶#小鹏科技日#，梁一鸣本鸣来了，给我发了工牌，像不像？把我整的这么温柔可惜没赶上食堂。付款时除了有价格，连卡路里等营养信息都会展示。羡慕在小鹏上班的同学们#何小鹏首次披露物理AI巨大进展#​​​2广州·广州小鹏科技园-T2北门​",
      "reposts": 5,
      "comments": 125,
      "likes": 122,
      "pics": [
        "https://tvax4.sinaimg.cn/crop.0.0.750.750.180/0085KfK1ly8h540v278acj30ku0kuzkp.jpg?KID=imgbed,tva&Expires=1762339476&ssig=G7KxzbFupu",
        "https://tva3.sinaimg.cn/crop.106.24.313.313.180/bd3ffc82gw1e8jk24rip0j20ei0d0tan.jpg?KID=imgbed,tva&Expires=1762339477&ssig=vgq0HfjgxJ",
        "https://h5.sinaimg.cn/upload/108/1866/2022/11/02/vvip_2.png",
        "https://wx3.sinaimg.cn/orj360/bd3ffc82gy1i719wzn3fej20u014079f.jpg",
        "https://wx1.sinaimg.cn/orj360/bd3ffc82gy1i719wfea7sj20u0140wiu.jpg",
        "https://wx2.sinaimg.cn/orj360/bd3ffc82gy1i719x060h4j20u0140grq.jpg",
        "https://wx3.sinaimg.cn/orj360/bd3ffc82gy1i719x0rkthj21400u0q9u.jpg",
        "https://wx1.sinaimg.cn/orj360/bd3ffc82gy1i719x1ag4rj20u0140td7.jpg",
        "https://tva1.sinaimg.cn/default/images/default_avatar_male_180.gif",
        "https://a.sinaimg.cn/mintra/pic/2201190827/32aria.png"
      ],
      "video": {
        "title": null,
        "cover": null,
        "duration": null,
        "streams": {
          "stream_url": "https://livephoto.us.sinaimg.cn/0026jpEtjx08sJUZPT9J0h0411002VXr0k01.mov?Expires=1762332277&ssig=mMiEXwgNZo&KID=unistore,video"
        }
      },
      "score": 52.7
    },
    {
      "id": "detail-6917918548124686801",
      "bid": null,
      "url": "https://weibo.com/7331622139/QcqFH4QAO?refer_flag=1001030103_",
      "created_at": "今天14:12",
      "user_id": null,
      "user_name": "小怡说车",
      "verified": null,
      "region": null,
      "source": "",
      "text": "#何小鹏首次披露物理AI巨大进展#今天小鹏科技日，小鹏董事长何小鹏要带着多项硬核技术成果重磅亮相，分享范围覆盖AI汽车、智能机器人、Robotaxi及飞行汽车等多个关键领域，展示小鹏汽车取得的突破进展～物理AI的核心理念，通过融合数字与物理世界的操作系统、数据以及物理运动能力，形成全新的智能形 ​展开c",
      "text_raw": "#何小鹏首次披露物理AI巨大进展#今天小鹏科技日，小鹏董事长何小鹏要带着多项硬核技术成果重磅亮相，分享范围覆盖AI汽车、智能机器人、Robotaxi及飞行汽车等多个关键领域，展示小鹏汽车取得的突破进展～物理AI的核心理念，通过融合数字与物理世界的操作系统、数据以及物理运动能力，形成全新的智能形 ​展开c",
      "reposts": 3,
      "comments": 9,
      "likes": 111,
      "pics": [
        "https://tvax4.sinaimg.cn/crop.0.0.750.750.180/0085KfK1ly8h540v278acj30ku0kuzkp.jpg?KID=imgbed,tva&Expires=1762339477&ssig=ASqp6r%2BvCF",
        "https://tvax4.sinaimg.cn/crop.0.0.1080.1080.180/0080aJPZly8h7k815nfi4j30u00u00ud.jpg?KID=imgbed,tva&Expires=1762339478&ssig=oeg6dxbSoV",
        "https://h5.sinaimg.cn/upload/108/1866/2022/11/02/vvip_2.png",
        "https://wx1.sinaimg.cn/orj360/0080aJPZgy1i71b5jq1mng30u0140x71.gif",
        "https://wx4.sinaimg.cn/orj360/0080aJPZgy1i71b5k7jxwj31400qo0xh.jpg",
        "https://wx2.sinaimg.cn/orj360/0080aJPZgy1i71b5kn8zgj31400qon6l.jpg",
        "https://wx2.sinaimg.cn/orj360/0080aJPZgy1i71b74xwang30m80tnu16.gif",
        "https://wx3.sinaimg.cn/orj360/0080aJPZgy1i71b7eo1ljg30m80tnx74.gif",
        "https://wx2.sinaimg.cn/orj360/0080aJPZgy1i71b7fc7frj31400qodqx.jpg",
        "https://wx2.sinaimg.cn/orj360/0080aJPZgy1i71b7ftjm7j31400qo7dg.jpg",
        "https://wx2.sinaimg.cn/orj360/0080aJPZgy1i71b7gj6f0j310k1jk163.jpg",
        "https://tva1.sinaimg.cn/default/images/default_avatar_male_180.gif",
        "https://a.sinaimg.cn/mintra/pic/2201190827/32aria.png"
      ],
      "video": {
        "title": null,
        "cover": null,
        "duration": null,
        "streams": {
          "stream_url": "https://g.us.sinaimg.cn/o0/oj3sbrx8lx08sJQ3zaqk0104120016XY0E010.mp4?label=gif_mp4&template=800x1068.28.0&ssig=V2%2FvHu3Eca&Expires=1762332278&KID=unistore,video"
        }
      },
      "score": 15.600000000000001
    },
    {
      "id": "detail-5772724370704271756",
      "bid": null,
      "url": "https://weibo.com/6187481826/QcqOrrdmj?refer_flag=1001030103_",
      "created_at": "今天14:33",
      "user_id": null,
      "user_name": "菊香小姐",
      "verified": null,
      "region": null,
      "source": "",
      "text": "2025 小鹏科技日【涌现】惊喜不断新办公大楼真的气派，小鹏全家族车型、IRON、汇天飞行汽车组团亮相，这波真的太酷炫了，科技感车企我只服小鹏！#小鹏科技日##何小鹏首次披露物理AI巨大进展#​",
      "text_raw": "2025 小鹏科技日【涌现】惊喜不断新办公大楼真的气派，小鹏全家族车型、IRON、汇天飞行汽车组团亮相，这波真的太酷炫了，科技感车企我只服小鹏！#小鹏科技日##何小鹏首次披露物理AI巨大进展#​",
      "reposts": 157,
      "comments": 353,
      "likes": 245,
      "pics": [
        "https://tvax4.sinaimg.cn/crop.0.0.750.750.180/0085KfK1ly8h540v278acj30ku0kuzkp.jpg?KID=imgbed,tva&Expires=1762339477&ssig=ASqp6r%2BvCF",
        "https://tvax2.sinaimg.cn/crop.0.0.512.512.180/006KK2FYly8hfpndvraeoj30e80e8wev.jpg?KID=imgbed,tva&Expires=1762339478&ssig=PBlwVb4sBs",
        "https://h5.sinaimg.cn/upload/108/1866/2022/11/02/vvip_2.png",
        "https://wx3.sinaimg.cn/orj360/006KK2FYgy1i71btmndjbj31hc0zk7cb.jpg",
        "https://wx2.sinaimg.cn/orj360/006KK2FYgy1i71bsxblkzj31hc0zk11f.jpg",
        "https://wx3.sinaimg.cn/orj360/006KK2FYgy1i71bsw5mmkj31hc0zkn2z.jpg",
        "https://wx4.sinaimg.cn/orj360/006KK2FYgy1i71bswh23kj31hc0zk79u.jpg",
        "https://wx1.sinaimg.cn/orj360/006KK2FYgy1i71bswvhlwj31hc0zkdpb.jpg",
        "https://wx1.sinaimg.cn/orj360/006KK2FYgy1i71bsvrdsxj31hc0zkdo7.jpg",
        "https://wx4.sinaimg.cn/orj360/006KK2FYgy1i71bsxobv5j31hc0zkn3t.jpg",
        "https://wx3.sinaimg.cn/orj360/006KK2FYgy1i71btn4eufj31hc0zk44s.jpg",
        "https://wx2.sinaimg.cn/orj360/006KK2FYgy1i71btm2j58j31hc0zkgs6.jpg",
        "https://tva1.sinaimg.cn/default/images/default_avatar_male_180.gif",
        "https://a.sinaimg.cn/mintra/pic/2201190827/32aria.png"
      ],
      "video": null,
      "score": 224.6
    },
    {
      "id": "detail-474579641355356526",
      "bid": null,
      "url": "https://weibo.com/3246612795/QcqHTzEvl?refer_flag=1001030103_",
      "created_at": "今天14:17",
      "user_id": null,
      "user_name": "水雾同学_DrEV",
      "verified": null,
      "region": null,
      "source": "",
      "text": "人就在广州小鹏新总部，一个字大。简单聊聊我看到的。先说结论，这家公司坚持技术研发，卷智能卷得很正，今年销量也一路往上走，市场给到反馈，这才是技术最好的证明。#何小鹏首次披露物理AI巨大进展#何小鹏这次讲的“物理AI”，用最直白的话说就是：以前的车靠一堆规则开车，现在小鹏要让车靠理 ​展开c",
      "text_raw": "人就在广州小鹏新总部，一个字大。简单聊聊我看到的。先说结论，这家公司坚持技术研发，卷智能卷得很正，今年销量也一路往上走，市场给到反馈，这才是技术最好的证明。#何小鹏首次披露物理AI巨大进展#何小鹏这次讲的“物理AI”，用最直白的话说就是：以前的车靠一堆规则开车，现在小鹏要让车靠理 ​展开c",
      "reposts": 20,
      "comments": 64,
      "likes": 99,
      "pics": [
        "https://tvax4.sinaimg.cn/crop.0.0.750.750.180/0085KfK1ly8h540v278acj30ku0kuzkp.jpg?KID=imgbed,tva&Expires=1762339477&ssig=ASqp6r%2BvCF",
        "https://tvax4.sinaimg.cn/crop.0.0.1023.1023.180/c183613bly8hxtd0c3lbdj20sg0sfdhe.jpg?KID=imgbed,tva&Expires=1762339478&ssig=K2twzE9m9a",
        "https://h5.sinaimg.cn/upload/108/1866/2022/11/02/vvip_1.png",
        "https://wx3.sinaimg.cn/orj360/c183613bgy1i71bf8ck85j20u0140n17.jpg",
        "https://wx4.sinaimg.cn/orj360/c183613bgy1i71bf8tocpj21400u0446.jpg",
        "https://wx1.sinaimg.cn/orj360/c183613bgy1i71bf9606oj21400u0jvx.jpg",
        "https://wx1.sinaimg.cn/orj360/c183613bgy1i71bf9lfmvj21400u00y5.jpg",
        "https://wx2.sinaimg.cn/orj360/c183613bgy1i71bfaeujrj21400u0jwh.jpg",
        "https://wx2.sinaimg.cn/orj360/c183613bgy1i71bfatyxnj21400u0jvf.jpg",
        "https://wx3.sinaimg.cn/orj360/c183613bgy1i71bfbxk1qj20sm0qmwj3.jpg",
        "https://wx2.sinaimg.cn/orj360/c183613bgy1i71bfcc45yj21400u0wjt.jpg",
        "https://wx2.sinaimg.cn/orj360/c183613bgy1i71bfctcsfj21400u0jy5.jpg",
        "https://tva1.sinaimg.cn/default/images/default_avatar_male_180.gif",
        "https://a.sinaimg.cn/mintra/pic/2201190827/32aria.png"
      ],
      "video": null,
      "score": 41.1
    },
    {
      "id": "detail-608347022001780923",
      "bid": null,
      "url": "https://weibo.com/2707480475/QcqDKtVaV?refer_flag=1001030103_",
      "created_at": "今天14:07",
      "user_id": null,
      "user_name": "Clownyx",
      "verified": null,
      "region": null,
      "source": "",
      "text": "看一下隔壁的小鹏汇天这也太未来了吧！见到了最新的A868高速长航程全倾转飞行汽车，被它的体量震撼到了！#小鹏科技日##何小鹏首次披露物理AI巨大进展##大v聊车#2广州·广州小鹏科技园-T2北门​",
      "text_raw": "看一下隔壁的小鹏汇天这也太未来了吧！见到了最新的A868高速长航程全倾转飞行汽车，被它的体量震撼到了！#小鹏科技日##何小鹏首次披露物理AI巨大进展##大v聊车#2广州·广州小鹏科技园-T2北门​",
      "reposts": 12,
      "comments": 49,
      "likes": 98,
      "pics": [
        "https://tvax4.sinaimg.cn/crop.0.0.750.750.180/0085KfK1ly8h540v278acj30ku0kuzkp.jpg?KID=imgbed,tva&Expires=1762339477&ssig=ASqp6r%2BvCF",
        "https://tvax4.sinaimg.cn/crop.0.0.1080.1080.180/a160df9bly8hs62992mhvj20u00u0dh1.jpg?KID=imgbed,tva&Expires=1762339478&ssig=CLWM4wVh8l",
        "https://h5.sinaimg.cn/upload/108/1866/2022/11/02/vvip_2.png",
        "https://wx2.sinaimg.cn/orj360/a160df9bgy1i71b14wb1mj235s1s0u0x.jpg",
        "https://wx3.sinaimg.cn/orj360/a160df9bgy1i71b18srppj235s1s07wh.jpg",
        "https://wx4.sinaimg.cn/orj360/a160df9bgy1i71b1aekg1j235s1s04qq.jpg",
        "https://wx1.sinaimg.cn/orj360/a160df9bgy1i71b1bng6hj235s1s07wh.jpg",
        "https://wx4.sinaimg.cn/orj360/a160df9bgy1i71bff7v2pj21s035se81.jpg",
        "https://wx2.sinaimg.cn/orj360/a160df9bgy1i71b1d29tgj235c1rsqv5.jpg",
        "https://wx2.sinaimg.cn/orj360/a160df9bgy1i71b1ek337j235s1s0npd.jpg",
        "https://wx2.sinaimg.cn/orj360/a160df9bgy1i71b1ggq71j235s1s07wi.jpg",
        "https://wx4.sinaimg.cn/orj360/a160df9bgy1i71b1hjmbgj235s1s0b29.jpg",
        "https://tva1.sinaimg.cn/default/images/default_avatar_male_180.gif",
        "https://a.sinaimg.cn/mintra/pic/2201190827/32aria.png"
      ],
      "video": null,
      "score": 31.7
    },
    {
      "id": "detail-1989136480664796872",
      "bid": null,
      "url": "https://weibo.com/3766814100/QcqIc9u3N?refer_flag=1001030103_",
      "created_at": "今天14:18",
      "user_id": null,
      "user_name": "梁小欣同学",
      "verified": null,
      "region": null,
      "source": "",
      "text": "#小鹏科技日#以“涌现”为主题，更像是一次未来生活剧透——何小鹏带着物理AI，把数字世界带进汽车、机器人这些看得见摸得着的东西里。比如第二代VLA技术，就像给车装了火眼金睛，复杂路况也能稳稳通过；还有能说多种语言的VLM座舱，以后开车时和它聊天，就像和懂你的朋友唠嗑最让人眼前一亮的是2026 ​展开c",
      "text_raw": "#小鹏科技日#以“涌现”为主题，更像是一次未来生活剧透——何小鹏带着物理AI，把数字世界带进汽车、机器人这些看得见摸得着的东西里。比如第二代VLA技术，就像给车装了火眼金睛，复杂路况也能稳稳通过；还有能说多种语言的VLM座舱，以后开车时和它聊天，就像和懂你的朋友唠嗑最让人眼前一亮的是2026 ​展开c",
      "reposts": 7,
      "comments": 82,
      "likes": 63,
      "pics": [
        "https://tvax4.sinaimg.cn/crop.0.0.750.750.180/0085KfK1ly8h540v278acj30ku0kuzkp.jpg?KID=imgbed,tva&Expires=1762339478&ssig=b34tnTLsMc",
        "https://tvax3.sinaimg.cn/crop.0.0.512.512.180/e0850594ly8hpn4hor0azj20e80e80ta.jpg?KID=imgbed,tva&Expires=1762339479&ssig=IZhIReIfXW",
        "https://h5.sinaimg.cn/upload/108/1866/2022/11/02/vvip_2.png",
        "https://wx1.sinaimg.cn/orj360/e0850594gy1i71bdmw4kgj22pu1t8x6q.jpg",
        "https://wx1.sinaimg.cn/orj360/e0850594gy1i71bdo0fu9j241b2ovnpf.jpg",
        "https://wx4.sinaimg.cn/orj360/e0850594gy1i71bdpkpwzj24mo334npg.jpg",
        "https://wx4.sinaimg.cn/orj360/e0850594gy1i71bdrmpadj24l23211l2.jpg",
        "https://wx3.sinaimg.cn/orj360/e0850594gy1i71bdt91iwj24kf31m4qs.jpg",
        "https://wx2.sinaimg.cn/orj360/e0850594gy1i71bdvv6c1j24ag2uzkjo.jpg",
        "https://wx3.sinaimg.cn/mw690/e0850594gy1hp022hbhh5j20u00u0zmz.jpg",
        "https://a.sinaimg.cn/mintra/pic/2201190827/32aria.png"
      ],
      "video": null,
      "score": 35.099999999999994
    },
    {
      "id": "detail-1961662920520700237",
      "bid": null,
      "url": "https://weibo.com/7397646384/Qcr26acee?refer_flag=1001030103_",
      "created_at": "36分钟前",
      "user_id": null,
      "user_name": "11AMYLIU",
      "verified": null,
      "region": null,
      "source": "",
      "text": "来了来了～又看到大师兄了～#小鹏科技日#今天是小鹏科技日，据说会发布四个AI方面的应用和进展，期待#何小鹏首次披露物理AI巨大进展#​",
      "text_raw": "来了来了～又看到大师兄了～#小鹏科技日#今天是小鹏科技日，据说会发布四个AI方面的应用和进展，期待#何小鹏首次披露物理AI巨大进展#​",
      "reposts": 32,
      "comments": 39,
      "likes": 40,
      "pics": [
        "https://tvax4.sinaimg.cn/crop.0.0.750.750.180/0085KfK1ly8h540v278acj30ku0kuzkp.jpg?KID=imgbed,tva&Expires=1762339478&ssig=b34tnTLsMc",
        "https://tvax1.sinaimg.cn/crop.0.0.1080.1080.180/0084DLLaly8i5dmdrzn1wj30u00u076d.jpg?KID=imgbed,tva&Expires=1762339479&ssig=5mC%2F7luTm7",
        "https://h5.sinaimg.cn/upload/108/1866/2022/11/02/vvip_2.png",
        "https://h5.sinaimg.cn/upload/1005/526/2021/02/02/feed_icon_community.png",
        "https://wx1.sinaimg.cn/orj360/0084DLLagy1i71cpppribj31be0zjjt8.jpg",
        "https://wx3.sinaimg.cn/mw690/0084DLLaly1hrz7drluhij30u00u0my2.jpg",
        "https://tvax1.sinaimg.cn/crop.0.0.1080.1080.180/0084DLLaly8i5dmdrzn1wj30u00u076d.jpg?KID=imgbed,tva&Expires=1762339480&ssig=Gt2jytusQ4",
        "https://a.sinaimg.cn/mintra/pic/2201190827/32aria.png"
      ],
      "video": null,
      "score": 34.9
    },
    {
      "id": "detail-4697283579921277350",
      "bid": null,
      "url": "https://weibo.com/3246612795/QcqYh3oWW?refer_flag=1001030103_",
      "created_at": "46分钟前",
      "user_id": null,
      "user_name": "水雾同学_DrEV",
      "verified": null,
      "region": null,
      "source": "",
      "text": "#何小鹏首次披露物理AI巨大进展#小鹏第七次科技日发布会。真科技无需过多铺张浪费，自己的演播厅，自己的舞台，还有现场好多老外啊，全球出海布局正在加快。小鹏是目前唯一完成2025年销售计划的新势力。#新能源大牛说#​",
      "text_raw": "#何小鹏首次披露物理AI巨大进展#小鹏第七次科技日发布会。真科技无需过多铺张浪费，自己的演播厅，自己的舞台，还有现场好多老外啊，全球出海布局正在加快。小鹏是目前唯一完成2025年销售计划的新势力。#新能源大牛说#​",
      "reposts": 17,
      "comments": 30,
      "likes": 53,
      "pics": [
        "https://tvax4.sinaimg.cn/crop.0.0.750.750.180/0085KfK1ly8h540v278acj30ku0kuzkp.jpg?KID=imgbed,tva&Expires=1762339478&ssig=b34tnTLsMc",
        "https://tvax4.sinaimg.cn/crop.0.0.1023.1023.180/c183613bly8hxtd0c3lbdj20sg0sfdhe.jpg?KID=imgbed,tva&Expires=1762339479&ssig=JB3l9GvaN5",
        "https://h5.sinaimg.cn/upload/108/1866/2022/11/02/vvip_1.png",
        "https://wx4.sinaimg.cn/orj360/c183613bgy1i71cgcbupej21400u0qa1.jpg",
        "https://wx1.sinaimg.cn/orj360/c183613bgy1i71cgjmua8j20r20kago5.jpg",
        "https://wx3.sinaimg.cn/orj360/c183613bgy1i71cgdc8l7j21400u0dmo.jpg",
        "https://wx3.sinaimg.cn/orj360/c183613bgy1i71cgduab2j21400u0agb.jpg",
        "https://wx3.sinaimg.cn/orj360/c183613bgy1i71cgedivoj21400u00zm.jpg",
        "https://wx1.sinaimg.cn/orj360/c183613bgy1i71cgf1vqwj21400u07bi.jpg",
        "https://wx1.sinaimg.cn/orj360/c183613bgy1i71cgfkmphj21400u0441.jpg",
        "https://wx3.sinaimg.cn/orj360/c183613bgy1i71cgg5fbwj21400u0n50.jpg",
        "https://wx1.sinaimg.cn/orj360/c183613bgy1i71cggmdrhj21400u0gq7.jpg",
        "https://tva1.sinaimg.cn/default/images/default_avatar_male_180.gif",
        "https://a.sinaimg.cn/mintra/pic/2201190827/32aria.png"
      ],
      "video": null,
      "score": 24.5
    },
    {
      "id": "detail-8524228358061739010",
      "bid": null,
      "url": "https://weibo.com/3246612795/Qcr0qzNsK?refer_flag=1001030103_",
      "created_at": "41分钟前",
      "user_id": null,
      "user_name": "水雾同学_DrEV",
      "verified": null,
      "region": null,
      "source": "",
      "text": "一看就是人老实，话不多。#何小鹏首次披露物理ai巨大进展#​",
      "text_raw": "一看就是人老实，话不多。#何小鹏首次披露物理ai巨大进展#​",
      "reposts": 14,
      "comments": 29,
      "likes": 57,
      "pics": [
        "https://tvax4.sinaimg.cn/crop.0.0.750.750.180/0085KfK1ly8h540v278acj30ku0kuzkp.jpg?KID=imgbed,tva&Expires=1762339478&ssig=b34tnTLsMc",
        "https://tvax4.sinaimg.cn/crop.0.0.1023.1023.180/c183613bly8hxtd0c3lbdj20sg0sfdhe.jpg?KID=imgbed,tva&Expires=1762339479&ssig=JB3l9GvaN5",
        "https://h5.sinaimg.cn/upload/108/1866/2022/11/02/vvip_1.png",
        "https://wx1.sinaimg.cn/orj360/c183613bgy1i71co2kbw6j21400u0gnr.jpg",
        "https://wx1.sinaimg.cn/orj360/c183613bgy1i71co2xv07j21400u0whw.jpg",
        "https://wx3.sinaimg.cn/orj360/c183613bgy1i71co3bu9qj21400u0n33.jpg",
        "https://wx3.sinaimg.cn/orj360/c183613bgy1i71co3s7uoj21400u0gps.jpg",
        "https://tvax4.sinaimg.cn/crop.0.0.40.40.50/008rzqllly4gyrdvcx4pyj30140140ls.jpg?KID=imgbed,tva&Expires=1762339479&ssig=9VgsmhZ10r",
        "https://h5.sinaimg.cn/upload/114/962/2022/07/08/member_2_bigfan1_1.png",
        "https://tvax4.sinaimg.cn/crop.0.0.800.800.50/006U2W42ly8i5wot2nrosj30m80m8myz.jpg?KID=imgbed,tva&Expires=1762339479&ssig=mMm%2FV8LVzQ",
        "https://h5.sinaimg.cn/upload/114/962/2022/07/08/member_0_bigfan1_3.png",
        "https://tvax1.sinaimg.cn/crop.0.0.1080.1080.50/007fEjOCly8i6chwynb08j30u00u0tbt.jpg?KID=imgbed,tva&Expires=1762339479&ssig=Tnwtr6%2B2jK",
        "https://h5.sinaimg.cn/upload/114/962/2022/07/08/member_1_bigfan1_1.png",
        "https://ww1.sinaimg.cn/mw690/549d0121tw1egm1kjly3jj20hs0hsq4f.jpg",
        "https://a.sinaimg.cn/mintra/pic/2201190827/32aria.png"
      ],
      "video": null,
      "score": 22.8
    },
    {
      "id": "detail-7735394743108797468",
      "bid": null,
      "url": "https://weibo.com/5316652868/QcrcgjqQN?refer_flag=1001030103_",
      "created_at": "11分钟前",
      "user_id": null,
      "user_name": "丁丁科技说",
      "verified": null,
      "region": null,
      "source": "",
      "text": "#何小鹏首次披露物理AI巨大进展#2025 小鹏科技日以「涌现Emergence」为题，是小鹏在过去技术积累至临界点后迎来的爆发点，更是在AI与物理世界的深度融合后，所迸发出的全新可能。不再单一去理解数字世界的AI革命和物理世界的新能源颠覆，小鹏从全栈自研的积累实践中逐步尝试跨域融合。而当AI与物理世 ​展开c",
      "text_raw": "#何小鹏首次披露物理AI巨大进展#2025 小鹏科技日以「涌现Emergence」为题，是小鹏在过去技术积累至临界点后迎来的爆发点，更是在AI与物理世界的深度融合后，所迸发出的全新可能。不再单一去理解数字世界的AI革命和物理世界的新能源颠覆，小鹏从全栈自研的积累实践中逐步尝试跨域融合。而当AI与物理世 ​展开c",
      "reposts": 48,
      "comments": 50,
      "likes": 50,
      "pics": [
        "https://tvax4.sinaimg.cn/crop.0.0.750.750.180/0085KfK1ly8h540v278acj30ku0kuzkp.jpg?KID=imgbed,tva&Expires=1762339479&ssig=ONwlp3Xsou",
        "https://tvax3.sinaimg.cn/crop.0.0.960.960.180/005NO8hCly8h8l2xax9qmj30qo0qomxz.jpg?KID=imgbed,tva&Expires=1762339480&ssig=oIrHeguKqj",
        "https://h5.sinaimg.cn/upload/108/1866/2022/11/02/vvip_2.png",
        "https://wx4.sinaimg.cn/orj360/005NO8hCly1i71diwrtatj33n421rnpd.jpg",
        "https://wx3.sinaimg.cn/orj360/005NO8hCly1i71dixuib4j33n421rnpd.jpg",
        "https://wx3.sinaimg.cn/orj360/005NO8hCly1i71diyu63bj33n421rkjl.jpg",
        "https://wx3.sinaimg.cn/orj360/005NO8hCly1i71divjh5jj33n421rkjm.jpg",
        "https://wx2.sinaimg.cn/mw690/74647f39ly1g5ch8sv5huj20u00u04c9.jpg",
        "https://tvax3.sinaimg.cn/crop.0.0.960.960.180/005NO8hCly8h8l2xax9qmj30qo0qomxz.jpg?KID=imgbed,tva&Expires=1762339481&ssig=nuo600dpRU",
        "https://a.sinaimg.cn/mintra/pic/2201190827/32aria.png"
      ],
      "video": null,
      "score": 48.8
    },
    {
      "id": "detail-1508064395397352249",
      "bid": null,
      "url": "https://weibo.com/2772978773/QcqCzuIcr?refer_flag=1001030103_",
      "created_at": "今天14:04",
      "user_id": null,
      "user_name": "GeeK老王",
      "verified": null,
      "region": null,
      "source": "",
      "text": "#何小鹏首次披露物理AI巨大进展#今天可是个大日子，2025年小鹏科技日正式拉开帷幕啦！这次主题定为“涌现”，相当有深意。小鹏汽车董事长何小鹏会带着涵盖AI汽车、智能机器人等多领域的硬核技术成果闪亮登场。此前他提出“物理AI”理念，指出数据是驱动硬件变革的核心，自研芯片与动力系统是释放潜力 ​展开c",
      "text_raw": "#何小鹏首次披露物理AI巨大进展#今天可是个大日子，2025年小鹏科技日正式拉开帷幕啦！这次主题定为“涌现”，相当有深意。小鹏汽车董事长何小鹏会带着涵盖AI汽车、智能机器人等多领域的硬核技术成果闪亮登场。此前他提出“物理AI”理念，指出数据是驱动硬件变革的核心，自研芯片与动力系统是释放潜力 ​展开c",
      "reposts": 20,
      "comments": 78,
      "likes": 104,
      "pics": [
        "https://tvax4.sinaimg.cn/crop.0.0.750.750.180/0085KfK1ly8h540v278acj30ku0kuzkp.jpg?KID=imgbed,tva&Expires=1762339480&ssig=AKKBUKjKdN",
        "https://tvax4.sinaimg.cn/crop.0.0.512.512.180/a5484c55ly8i394ro8h7dj20e80e83yp.jpg?KID=imgbed,tva&Expires=1762339481&ssig=%2BkwCdb8m%2BF",
        "https://h5.sinaimg.cn/upload/108/1866/2022/11/02/vvip_2.png",
        "https://wx2.sinaimg.cn/orj360/a5484c55ly1i71az4mycij20j60cswip.jpg",
        "https://wx4.sinaimg.cn/orj360/a5484c55ly1i71az4par7j20j60csdji.jpg",
        "https://wx4.sinaimg.cn/orj360/a5484c55ly1i71az4pmbqj20j60cswim.jpg",
        "https://wx1.sinaimg.cn/orj480/a5484c55ly1i71azg3kcqj20k00z8mz2.jpg",
        "https://wx1.sinaimg.cn/orj360/a5484c55ly1i71az4pp8fj20j60csq5n.jpg",
        "https://tva1.sinaimg.cn/default/images/default_avatar_male_180.gif",
        "https://a.sinaimg.cn/mintra/pic/2201190827/32aria.png"
      ],
      "video": null,
      "score": 45.8
    },
    {
      "id": "detail-273823936243369220",
      "bid": null,
      "url": "https://weibo.com/6933884384/QcqBhheZN?refer_flag=1001030103_",
      "created_at": "今天14:01",
      "user_id": null,
      "user_name": "LeoGo科技",
      "verified": null,
      "region": null,
      "source": "",
      "text": "#小鹏科技日#我喜欢【涌现】的主题！更喜欢的是，何小鹏关于Robotaxi的一些设想！我们也看到了小鹏全家族车型、IRON、汇天飞行汽车组团登场！期待，#何小鹏首次披露物理AI巨大进展#​",
      "text_raw": "#小鹏科技日#我喜欢【涌现】的主题！更喜欢的是，何小鹏关于Robotaxi的一些设想！我们也看到了小鹏全家族车型、IRON、汇天飞行汽车组团登场！期待，#何小鹏首次披露物理AI巨大进展#​",
      "reposts": 2,
      "comments": 51,
      "likes": 68,
      "pics": [
        "https://tvax4.sinaimg.cn/crop.0.0.750.750.180/0085KfK1ly8h540v278acj30ku0kuzkp.jpg?KID=imgbed,tva&Expires=1762339480&ssig=AKKBUKjKdN",
        "https://tvax2.sinaimg.cn/crop.0.0.1080.1080.180/007zfS4Uly8hwnvj6rd9rj30u00u0wg2.jpg?KID=imgbed,tva&Expires=1762339481&ssig=kkJnoSrT%2Fc",
        "https://h5.sinaimg.cn/upload/108/1866/2022/11/02/vvip_2.png",
        "https://wx1.sinaimg.cn/orj360/007zfS4Uly1i71avendxxj31jk2qtx5i.jpg",
        "https://wx1.sinaimg.cn/orj360/007zfS4Uly1i71avey6g7j31hc0zkagg.jpg",
        "https://wx4.sinaimg.cn/orj360/007zfS4Uly1i71avfawj7j318g0tn7p4.jpg",
        "https://wx3.sinaimg.cn/orj360/007zfS4Uly1i71avfmr6bj318g0tn4a1.jpg",
        "https://wx3.sinaimg.cn/orj360/007zfS4Uly1i71avfwcekj31hc0zkdlr.jpg",
        "https://wx1.sinaimg.cn/orj360/007zfS4Uly1i71avg67qjj318g0tn4ab.jpg",
        "https://wx4.sinaimg.cn/orj360/007zfS4Uly1i71ave771ej318g0tn7kv.jpg",
        "https://wx1.sinaimg.cn/orj360/007zfS4Uly1i71avgkxxxj318g0tnh1a.jpg",
        "https://wx2.sinaimg.cn/orj360/007zfS4Uly1i71avgz7ohj31hc0zkjzu.jpg",
        "https://wx3.sinaimg.cn/mw690/007zfS4Uly1hpc5kn7pw8j30u00u0q3b.jpg",
        "https://a.sinaimg.cn/mintra/pic/2201190827/32aria.png"
      ],
      "video": null,
      "score": 23.3
    },
    {
      "id": "detail-7692434041983536187",
      "bid": null,
      "url": "https://weibo.com/1644088831/QcqovvZ7v?refer_flag=1001030103_",
      "created_at": "今天13:30",
      "user_id": null,
      "user_name": "新浪汽车",
      "verified": null,
      "region": null,
      "source": "",
      "text": "#何小鹏首次披露物理AI巨大进展#今日，@小鹏汽车正式拉开2025年小鹏科技日的大幕，主题为“涌现”。小鹏汽车董事长兼CEO何小鹏将携多项硬核技术成果重磅亮相，分享范围覆盖AI汽车、智能机器人、Robotaxi及飞行汽车等多个关键领域，集中展示小鹏汽车取得的多维度突破性进展。@XP-何小鹏此前曾阐释 ​展开c",
      "text_raw": "#何小鹏首次披露物理AI巨大进展#今日，@小鹏汽车正式拉开2025年小鹏科技日的大幕，主题为“涌现”。小鹏汽车董事长兼CEO何小鹏将携多项硬核技术成果重磅亮相，分享范围覆盖AI汽车、智能机器人、Robotaxi及飞行汽车等多个关键领域，集中展示小鹏汽车取得的多维度突破性进展。@XP-何小鹏此前曾阐释 ​展开c",
      "reposts": 1010,
      "comments": 1724,
      "likes": 1547,
      "pics": [
        "https://tvax4.sinaimg.cn/crop.0.0.750.750.180/0085KfK1ly8h540v278acj30ku0kuzkp.jpg?KID=imgbed,tva&Expires=1762339480&ssig=AKKBUKjKdN",
        "https://tvax2.sinaimg.cn/crop.0.0.1005.1005.180/001NgqBNly8h8vcyq32hdj60rx0rxt9j02.jpg?KID=imgbed,tva&Expires=1762339481&ssig=XwP4Sxht6s",
        "https://h5.sinaimg.cn/upload/108/1866/2022/11/02/vip_7.png",
        "https://wx1.sinaimg.cn/orj480/001NgqBNly1i717e9ue8jj60u01gyq6k02.jpg",
        "https://wx2.sinaimg.cn/orj360/001NgqBNgy1i717du2a4fg60u0140x7102.gif",
        "https://wx2.sinaimg.cn/orj360/001NgqBNgy1i717dwr28ng60m80tnx7402.gif",
        "https://wx3.sinaimg.cn/orj360/001NgqBNgy1i717dqgyprg60m80tnu1602.gif",
        "https://wx1.sinaimg.cn/orj360/001NgqBNgy1i717di2pj0j644n2r34qr02.jpg",
        "https://wx4.sinaimg.cn/orj360/001NgqBNgy1i717di4hh9j64l2321qv902.jpg",
        "https://wx1.sinaimg.cn/orj360/001NgqBNgy1i717die2rlj64fu2ykx6t02.jpg",
        "https://wx4.sinaimg.cn/orj360/001NgqBNgy1i717dij955j64m732tx6t02.jpg",
        "https://wx2.sinaimg.cn/mw690/61fecdffly1fp1r410i0ij20yi0yiwhl.jpg",
        "https://a.sinaimg.cn/mintra/pic/2201190827/32aria.png"
      ],
      "video": {
        "title": null,
        "cover": null,
        "duration": null,
        "streams": {
          "stream_url": "https://g.us.sinaimg.cn/o0/nI7UBuOelx08sJN9iXkQ0104120016XY0E010.mp4?label=gif_mp4&template=800x1068.28.0&ssig=ridW5%2Fg6Qi&Expires=1762332281&KID=unistore,video"
        }
      },
      "score": 1277.8999999999999
    },
    {
      "id": "detail-564503761267222792",
      "bid": null,
      "url": "https://weibo.com/2039556740/QcqV8re3w?refer_flag=1001030103_",
      "created_at": "54分钟前",
      "user_id": null,
      "user_name": "科技数码说",
      "verified": null,
      "region": null,
      "source": "",
      "text": "#小鹏科技日#我鹏是真好起来了international Media我来了#何小鹏首次披露物理AI巨大进展#​​​",
      "text_raw": "#小鹏科技日#我鹏是真好起来了international Media我来了#何小鹏首次披露物理AI巨大进展#​​​",
      "reposts": 7,
      "comments": 10,
      "likes": 31,
      "pics": [
        "https://tvax4.sinaimg.cn/crop.0.0.750.750.180/0085KfK1ly8h540v278acj30ku0kuzkp.jpg?KID=imgbed,tva&Expires=1762339481&ssig=IZisOABFTX",
        "https://tvax2.sinaimg.cn/crop.0.0.1080.1080.180/79912a84ly8hpzevwxc1jj20u00u0jt2.jpg?KID=imgbed,tva&Expires=1762339482&ssig=OVR3guiMLQ",
        "https://h5.sinaimg.cn/upload/108/1866/2022/11/02/vvip_2.png",
        "https://wx3.sinaimg.cn/orj360/79912a84gy1i71cb1lkq8j22dc35cqrb.jpg",
        "https://ww1.sinaimg.cn/mw690/549d0121tw1egm1kjly3jj20hs0hsq4f.jpg",
        "https://a.sinaimg.cn/mintra/pic/2201190827/32aria.png"
      ],
      "video": null,
      "score": 10.3
    }
  ]
}