{
  "topic": "#被蛇咬后失联的网红已找到#",
  "fetched_at": "2025-10-29T10:17:11+08:00",
  "total": 15,
  "top_n": 30,
  "items": [
    {
      "id": "detail-4559315508637819217",
      "bid": null,
      "url": "https://weibo.com/2318910945/QbfIw2aTy?refer_flag=1001030103_",
      "created_at": "10月28日 20:28",
      "user_id": null,
      "user_name": "新浪热点",
      "verified": null,
      "region": null,
      "source": "",
      "text": "【#被蛇咬后失联的网红已找到#】#被蛇咬后嫌血清贵失联的网红已找到#10月27日，有网友发视频称，湖南邵阳洞口县有一名男子尹华健在直播挖蛇时被蛇咬伤，他到医院检查后嫌血清贵自行离开，至今下落不明。如今两天过去，当地的公安机关、救援力量经过大规模搜救，仍未有尹华健的消息。10月28日下午， ​展开c",
      "text_raw": "【#被蛇咬后失联的网红已找到#】#被蛇咬后嫌血清贵失联的网红已找到#10月27日，有网友发视频称，湖南邵阳洞口县有一名男子尹华健在直播挖蛇时被蛇咬伤，他到医院检查后嫌血清贵自行离开，至今下落不明。如今两天过去，当地的公安机关、救援力量经过大规模搜救，仍未有尹华健的消息。10月28日下午， ​展开c",
      "reposts": 145,
      "comments": 635,
      "likes": 7875,
      "pics": [
        "https://tvax4.sinaimg.cn/crop.0.0.750.750.180/0085KfK1ly8h540v278acj30ku0kuzkp.jpg?KID=imgbed,tva&Expires=1761715027&ssig=Aczkw4uBui",
        "https://tvax3.sinaimg.cn/crop.0.0.450.450.180/002wVUFrly8h8vgt7mcs2j60ci0ci0t002.jpg?KID=imgbed,tva&Expires=1761715028&ssig=gbkb0NS6qD",
        "https://h5.sinaimg.cn/upload/108/1866/2022/11/02/vvip_3.png",
        "https://h5.sinaimg.cn/upload/2015/09/25/3/timeline_card_small_video_default.png",
        "https://tvax1.sinaimg.cn/crop.0.0.179.179.1024/001R3oqEly8h8vg5q4wzdj604z04z3yf02.jpg?KID=imgbed,tva&Expires=1761715028&ssig=Z2an37IhAp",
        "https://tva1.sinaimg.cn/default/images/default_avatar_male_180.gif",
        "https://a.sinaimg.cn/mintra/pic/2201190827/32aria.png"
      ],
      "video": {
        "title": null,
        "cover": null,
        "duration": null,
        "streams": {
          "stream_url": "https://f.video.weibocdn.com/o0/MpcucvWblx08sxpZrVji010412006d5I0E010.mp4?label=mp4_720p&template=720x1280.24.0&media_id=5226802650742920&tp=8x8A3El:YTkl0eM8&us=0&ori=1&bf=4&ot=v&lp=0000fND37&ps=mZ6WB&uid=85KfK1&ab=,15568-g4,8012-g2,3601-g43,8013-g0,3601-g36&Expires=1761707828&ssig=NtDNAaWi%2FX&KID=unistore,video"
        }
      },
      "score": 1065.0
    },
    {
      "id": "detail-4807679908494099999",
      "bid": null,
      "url": "https://weibo.com/3884286575/Qbk3xjnY9?refer_flag=1001030103_",
      "created_at": "今天07:31",
      "user_id": null,
      "user_name": "我被安利了",
      "verified": null,
      "region": null,
      "source": "",
      "text": "#被蛇咬后失联的网红已找到#不能为了流量而不顾自己的生命安全，要对大自然要保持敬畏！时刻要记住，生命重于一切！ ​",
      "text_raw": "#被蛇咬后失联的网红已找到#不能为了流量而不顾自己的生命安全，要对大自然要保持敬畏！时刻要记住，生命重于一切！ ​",
      "reposts": 0,
      "comments": 20,
      "likes": 163,
      "pics": [
        "https://tvax4.sinaimg.cn/crop.0.0.750.750.180/0085KfK1ly8h540v278acj30ku0kuzkp.jpg?KID=imgbed,tva&Expires=1761715027&ssig=Aczkw4uBui",
        "https://tvax1.sinaimg.cn/crop.0.0.461.461.180/e785826fly8hrihpp55gkj20ct0ctjs6.jpg?KID=imgbed,tva&Expires=1761715028&ssig=6NIbWz1H5r",
        "https://h5.sinaimg.cn/upload/108/1866/2022/11/02/vvip_2.png",
        "https://wx2.sinaimg.cn/orj480/e785826fly1i6sw9uleusj20u01hcwh3.jpg",
        "https://wx1.sinaimg.cn/orj360/e785826fgy1i6sw9s1styj21401hcgoc.jpg",
        "https://tva1.sinaimg.cn/default/images/default_avatar_male_180.gif",
        "https://a.sinaimg.cn/mintra/pic/2201190827/32aria.png"
      ],
      "video": null,
      "score": 22.3
    },
    {
      "id": "detail-3128296699008907710",
      "bid": null,
      "url": "https://weibo.com/2423757750/QbkjKlUvJ?refer_flag=1001030103_",
      "created_at": "今天08:11",
      "user_id": null,
      "user_name": "白衣山猫",
      "verified": null,
      "region": null,
      "source": "",
      "text": "#被蛇咬后失联的网红已找到#过了两天，他还能活着，说明他根本没有被银环蛇咬伤！难怪他不肯打抗银环蛇毒血清！但想不通，他为什么要假装被银环蛇咬过，还装模作样地去医院？#被蛇咬后嫌血清贵失联的网红已找到#​",
      "text_raw": "#被蛇咬后失联的网红已找到#过了两天，他还能活着，说明他根本没有被银环蛇咬伤！难怪他不肯打抗银环蛇毒血清！但想不通，他为什么要假装被银环蛇咬过，还装模作样地去医院？#被蛇咬后嫌血清贵失联的网红已找到#​",
      "reposts": 12,
      "comments": 52,
      "likes": 182,
      "pics": [
        "https://tvax4.sinaimg.cn/crop.0.0.750.750.180/0085KfK1ly8h540v278acj30ku0kuzkp.jpg?KID=imgbed,tva&Expires=1761715027&ssig=Aczkw4uBui",
        "https://tva1.sinaimg.cn/crop.2.0.1238.1238.180/90779bb6jw8f083jo2ckmj20yi0yedhn.jpg?KID=imgbed,tva&Expires=1761715028&ssig=up1U29odyT",
        "https://h5.sinaimg.cn/upload/108/1866/2022/11/02/vvip_2.png",
        "https://wx3.sinaimg.cn/orj360/002E1Q6Wgy1i6sxfn9xfej610o1yie2602.jpg",
        "https://tva1.sinaimg.cn/default/images/default_avatar_male_180.gif",
        "https://a.sinaimg.cn/mintra/pic/2201190827/32aria.png"
      ],
      "video": null,
      "score": 41.0
    },
    {
      "id": "detail-5323239637422495855",
      "bid": null,
      "url": "https://weibo.com/7067445147/Qbkgx3tPw?refer_flag=1001030103_",
      "created_at": "今天08:03",
      "user_id": null,
      "user_name": "只在今天说爱你",
      "verified": null,
      "region": null,
      "source": "",
      "text": "#被蛇咬后失联的网红已找到#直播挖蛇除了想博取流量还能是什么看见警车就跑了还以为是来抓自己罚款的，原来是要找他的 ​",
      "text_raw": "#被蛇咬后失联的网红已找到#直播挖蛇除了想博取流量还能是什么看见警车就跑了还以为是来抓自己罚款的，原来是要找他的 ​",
      "reposts": 0,
      "comments": 11,
      "likes": 73,
      "pics": [
        "https://tvax4.sinaimg.cn/crop.0.0.750.750.180/0085KfK1ly8h540v278acj30ku0kuzkp.jpg?KID=imgbed,tva&Expires=1761715027&ssig=Aczkw4uBui",
        "https://tvax4.sinaimg.cn/crop.0.0.1080.1080.180/007IihkLly8i6lk2u9hr9j30u00u076o.jpg?KID=imgbed,tva&Expires=1761715028&ssig=Tmm5j3dh22",
        "https://h5.sinaimg.cn/upload/108/1866/2022/11/02/vvip_1.png",
        "https://wx1.sinaimg.cn/orj480/007IihkLly1i6sx7frr36j30u01hc41w.jpg",
        "https://wx2.sinaimg.cn/orj360/007IihkLgy1i6sx7ai0z2j30wr0kc76z.jpg",
        "https://tva1.sinaimg.cn/default/images/default_avatar_male_180.gif",
        "https://a.sinaimg.cn/mintra/pic/2201190827/32aria.png"
      ],
      "video": null,
      "score": 10.600000000000001
    },
    {
      "id": "detail-7441710927176022250",
      "bid": null,
      "url": "https://weibo.com/2028810631/QbfRqe8eq?refer_flag=1001030103_",
      "created_at": "10月28日 20:50",
      "user_id": null,
      "user_name": "新浪新闻",
      "verified": null,
      "region": null,
      "source": "",
      "text": "【#被银环蛇咬伤失联网红已被找到#】#知情人称被蛇咬伤失联网红人没事#据三湘都市报，10月27日，有网友发视频称，湖南邵阳洞口县有一名男子尹华健在直播挖蛇时被蛇咬伤，他到医院检查后嫌血清贵自行离开，至今下落不明。如今两天过去，当地的公安机关、救援力量经过大规模搜救，仍未有尹华健的消息 ​展开c",
      "text_raw": "【#被银环蛇咬伤失联网红已被找到#】#知情人称被蛇咬伤失联网红人没事#据三湘都市报，10月27日，有网友发视频称，湖南邵阳洞口县有一名男子尹华健在直播挖蛇时被蛇咬伤，他到医院检查后嫌血清贵自行离开，至今下落不明。如今两天过去，当地的公安机关、救援力量经过大规模搜救，仍未有尹华健的消息 ​展开c",
      "reposts": 18,
      "comments": 49,
      "likes": 224,
      "pics": [
        "https://tvax4.sinaimg.cn/crop.0.0.750.750.180/0085KfK1ly8h540v278acj30ku0kuzkp.jpg?KID=imgbed,tva&Expires=1761715028&ssig=N0HQXBhID1",
        "https://tvax4.sinaimg.cn/crop.0.0.799.799.180/002diGk7ly8h8vg36oqidj60m70m7mxs02.jpg?KID=imgbed,tva&Expires=1761715029&ssig=3mnDXbMxMa",
        "https://h5.sinaimg.cn/upload/108/1866/2022/11/02/vvip_2.png",
        "https://h5.sinaimg.cn/upload/2015/09/25/3/timeline_card_small_video_default.png",
        "https://tvax1.sinaimg.cn/crop.0.0.179.179.1024/001R3oqEly8h8vg5q4wzdj604z04z3yf02.jpg?KID=imgbed,tva&Expires=1761715029&ssig=ym7DBTEmdg",
        "https://tva1.sinaimg.cn/default/images/default_avatar_male_180.gif",
        "https://a.sinaimg.cn/mintra/pic/2201190827/32aria.png"
      ],
      "video": {
        "title": null,
        "cover": null,
        "duration": null,
        "streams": {
          "stream_url": "https://f.video.weibocdn.com/o0/MpcucvWblx08sxpZrVji010412006d5I0E010.mp4?label=mp4_720p&template=720x1280.24.0&media_id=5226802650742920&tp=8x8A3El:YTkl0eM8&us=0&ori=1&bf=4&ot=v&lp=0000fND37&ps=mZ6WB&uid=85KfK1&ab=,15568-g4,8012-g2,3601-g43,8013-g0,3601-g36&Expires=1761707829&ssig=TPW%2FmI%2Bn5%2F&KID=unistore,video"
        }
      },
      "score": 47.900000000000006
    },
    {
      "id": "detail-4983270364548992942",
      "bid": null,
      "url": "https://weibo.com/3870605008/QbkmKcJtU?refer_flag=1001030103_",
      "created_at": "今天08:18",
      "user_id": null,
      "user_name": "青柠柠檬汁儿",
      "verified": null,
      "region": null,
      "source": "",
      "text": "#被蛇咬后失联的网红已找到#要么不是毒蛇咬伤，要么压根就没被蛇咬，被毒蛇咬了都有生命危险基本常识，要钱还是要命正常人都会选择生命，反常的举动背后，一定是有原因的… ​",
      "text_raw": "#被蛇咬后失联的网红已找到#要么不是毒蛇咬伤，要么压根就没被蛇咬，被毒蛇咬了都有生命危险基本常识，要钱还是要命正常人都会选择生命，反常的举动背后，一定是有原因的… ​",
      "reposts": 0,
      "comments": 16,
      "likes": 60,
      "pics": [
        "https://tvax4.sinaimg.cn/crop.0.0.750.750.180/0085KfK1ly8h540v278acj30ku0kuzkp.jpg?KID=imgbed,tva&Expires=1761715028&ssig=N0HQXBhID1",
        "https://tvax1.sinaimg.cn/crop.0.0.1080.1080.180/e6b4bed0ly8i1d2h83rfnj20u00u0af8.jpg?KID=imgbed,tva&Expires=1761715029&ssig=JScVyrFDYW",
        "https://h5.sinaimg.cn/upload/108/1866/2022/11/02/vvip_1.png",
        "https://wx2.sinaimg.cn/mw690/e6b4bed0ly1hokjys5v4vj20u00u0jx4.jpg",
        "https://a.sinaimg.cn/mintra/pic/2201190827/32aria.png"
      ],
      "video": null,
      "score": 10.8
    },
    {
      "id": "detail-3913590099912370113",
      "bid": null,
      "url": "https://weibo.com/1700087532/Qbfgbckx3?refer_flag=1001030103_",
      "created_at": "10月28日 19:18",
      "user_id": null,
      "user_name": "三湘都市报",
      "verified": null,
      "region": null,
      "source": "",
      "text": "【#疑被蛇咬后失联的网红和车辆已找到#】#救援人员连续两天搜救疑被蛇咬网红#10月27日，有网友发视频称，湖南邵阳洞口县有一名男子尹华健在直播挖蛇时被蛇咬伤，他到医院检查后嫌血清贵自行离开，至今下落不明。如今两天过去，当地的公安机关、救援力量经过大规模搜救，仍未有尹华健的消息。10月28日 ​展开c",
      "text_raw": "【#疑被蛇咬后失联的网红和车辆已找到#】#救援人员连续两天搜救疑被蛇咬网红#10月27日，有网友发视频称，湖南邵阳洞口县有一名男子尹华健在直播挖蛇时被蛇咬伤，他到医院检查后嫌血清贵自行离开，至今下落不明。如今两天过去，当地的公安机关、救援力量经过大规模搜救，仍未有尹华健的消息。10月28日 ​展开c",
      "reposts": 22,
      "comments": 29,
      "likes": 352,
      "pics": [
        "https://tvax4.sinaimg.cn/crop.0.0.750.750.180/0085KfK1ly8h540v278acj30ku0kuzkp.jpg?KID=imgbed,tva&Expires=1761715028&ssig=N0HQXBhID1",
        "https://tvax1.sinaimg.cn/crop.0.0.179.179.180/001R3oqEly8h8vg5q4wzdj604z04z3yf02.jpg?KID=imgbed,tva&Expires=1761715029&ssig=F1HUNsescW",
        "https://h5.sinaimg.cn/upload/108/1866/2022/11/02/vvip_2.png",
        "https://h5.sinaimg.cn/upload/2015/09/25/3/timeline_card_small_video_default.png",
        "https://tvax1.sinaimg.cn/crop.0.0.179.179.1024/001R3oqEly8h8vg5q4wzdj604z04z3yf02.jpg?KID=imgbed,tva&Expires=1761715029&ssig=ym7DBTEmdg",
        "https://tva1.sinaimg.cn/default/images/default_avatar_male_180.gif",
        "https://a.sinaimg.cn/mintra/pic/2201190827/32aria.png"
      ],
      "video": {
        "title": null,
        "cover": null,
        "duration": null,
        "streams": {
          "stream_url": "https://f.video.weibocdn.com/o0/MpcucvWblx08sxpZrVji010412006d5I0E010.mp4?label=mp4_720p&template=720x1280.24.0&media_id=5226802650742920&tp=8x8A3El:YTkl0eM8&us=0&ori=1&bf=4&ot=v&lp=0000fND37&ps=mZ6WB&uid=85KfK1&ab=,15568-g4,8012-g2,3601-g43,8013-g0,3601-g36&Expires=1761707829&ssig=TPW%2FmI%2Bn5%2F&KID=unistore,video"
        }
      },
      "score": 57.1
    },
    {
      "id": "detail-5730255938616100292",
      "bid": null,
      "url": "https://weibo.com/6355649753/QbkgL4w5d?refer_flag=1001030103_",
      "created_at": "今天08:04",
      "user_id": null,
      "user_name": "飞鱼Tech",
      "verified": null,
      "region": null,
      "source": "",
      "text": "#被蛇咬后失联的网红已找到#基本情况是以为直播抓蛇违法，看这么多警察来了吓得赶紧跑路吧​",
      "text_raw": "#被蛇咬后失联的网红已找到#基本情况是以为直播抓蛇违法，看这么多警察来了吓得赶紧跑路吧​",
      "reposts": 1,
      "comments": 1,
      "likes": 51,
      "pics": [
        "https://tvax4.sinaimg.cn/crop.0.0.750.750.180/0085KfK1ly8h540v278acj30ku0kuzkp.jpg?KID=imgbed,tva&Expires=1761715028&ssig=N0HQXBhID1",
        "https://tvax2.sinaimg.cn/crop.0.0.996.996.180/006W7EPTly8gdi6ax7inuj30ro0ro76t.jpg?KID=imgbed,tva&Expires=1761715029&ssig=I2t%2FSfSo%2Fy",
        "https://h5.sinaimg.cn/upload/108/1866/2022/11/02/vvip_2.png",
        "https://wx3.sinaimg.cn/orj360/006W7EPTly1i6sx8705ctj30u01de1kx.jpg",
        "https://tva1.sinaimg.cn/default/images/default_avatar_male_180.gif",
        "https://a.sinaimg.cn/mintra/pic/2201190827/32aria.png"
      ],
      "video": null,
      "score": 6.0
    },
    {
      "id": "detail-8724156477729414445",
      "bid": null,
      "url": "https://weibo.com/7324728426/QbjXavxAm?refer_flag=1001030103_",
      "created_at": "今天07:15",
      "user_id": null,
      "user_name": "紫轩冰凌_",
      "verified": null,
      "region": null,
      "source": "",
      "text": "#被蛇咬后失联的网红已找到#直播捕蛇都谁在看啊！听听就毛孔悚然！人没事就好。被毒蛇咬伤的伤口和无毒的蛇咬伤的伤口是有区别的。他既然敢捕蛇应该有些常识吧！万物皆有灵，要抱有敬畏之心 ​",
      "text_raw": "#被蛇咬后失联的网红已找到#直播捕蛇都谁在看啊！听听就毛孔悚然！人没事就好。被毒蛇咬伤的伤口和无毒的蛇咬伤的伤口是有区别的。他既然敢捕蛇应该有些常识吧！万物皆有灵，要抱有敬畏之心 ​",
      "reposts": 3,
      "comments": 36,
      "likes": 109,
      "pics": [
        "https://tvax4.sinaimg.cn/crop.0.0.750.750.180/0085KfK1ly8h540v278acj30ku0kuzkp.jpg?KID=imgbed,tva&Expires=1761715029&ssig=wc644neNRS",
        "https://tvax2.sinaimg.cn/crop.0.0.690.690.180/007ZHOt4ly8h8prk8g354j30j60j6abv.jpg?KID=imgbed,tva&Expires=1761715030&ssig=QayPd28ZcS",
        "https://h5.sinaimg.cn/upload/108/1866/2022/11/02/vvip_1.png",
        "https://tva1.sinaimg.cn/default/images/default_avatar_male_180.gif",
        "https://a.sinaimg.cn/mintra/pic/2201190827/32aria.png"
      ],
      "video": null,
      "score": 23.5
    },
    {
      "id": "detail-810281916647203736",
      "bid": null,
      "url": "https://weibo.com/1747150823/QbkINFqY0?refer_flag=1001030103_",
      "created_at": "今天09:13",
      "user_id": null,
      "user_name": "深圳县令",
      "verified": null,
      "region": null,
      "source": "",
      "text": "湖南邵阳59岁网红尹某直播挖蛇时被银环蛇咬伤，因嫌1400元/支的血清费用过高，未治疗便自行离院失联。经多方搜寻，其已被找到且人身安全，此前曾在亲戚家暂住并敷草药。事件引发热议，既凸显高危直播的安全隐患，也让人关注生命安全与医疗成本的权衡。#被蛇咬后失联的网红已找到#​展开c",
      "text_raw": "湖南邵阳59岁网红尹某直播挖蛇时被银环蛇咬伤，因嫌1400元/支的血清费用过高，未治疗便自行离院失联。经多方搜寻，其已被找到且人身安全，此前曾在亲戚家暂住并敷草药。事件引发热议，既凸显高危直播的安全隐患，也让人关注生命安全与医疗成本的权衡。#被蛇咬后失联的网红已找到#​展开c",
      "reposts": 23,
      "comments": 23,
      "likes": 19,
      "pics": [
        "https://tvax4.sinaimg.cn/crop.0.0.750.750.180/0085KfK1ly8h540v278acj30ku0kuzkp.jpg?KID=imgbed,tva&Expires=1761715030&ssig=lGAJiygakH",
        "https://tvax3.sinaimg.cn/crop.0.0.1006.1006.180/682367e7ly8fgt1568xmhj20ry0ryabo.jpg?KID=imgbed,tva&Expires=1761715030&ssig=3paDR7cWeP",
        "https://h5.sinaimg.cn/upload/108/1866/2022/11/02/vvip_2.png",
        "https://h5.sinaimg.cn/upload/2015/09/25/3/timeline_card_small_video_default.png",
        "https://tvax3.sinaimg.cn/crop.0.0.1006.1006.1024/682367e7ly8fgt1568xmhj20ry0ryabo.jpg?KID=imgbed,tva&Expires=1761715030&ssig=2c0%2BPhXCjE",
        "https://ww1.sinaimg.cn/mw690/549d0121tw1egm1kjly3jj20hs0hsq4f.jpg",
        "https://tvax3.sinaimg.cn/crop.0.0.1006.1006.180/682367e7ly8fgt1568xmhj20ry0ryabo.jpg?KID=imgbed,tva&Expires=1761715031&ssig=Ti9sf%2Bp55i",
        "https://a.sinaimg.cn/mintra/pic/2201190827/32aria.png"
      ],
      "video": {
        "title": null,
        "cover": null,
        "duration": null,
        "streams": {
          "stream_url": "https://f.video.weibocdn.com/u0/nUkScqlmgx08sylhuh2U01041200nzPn0E010.mp4?label=mp4_720p&template=576x1024.24.0&media_id=5227012554424342&tp=8x8A3El:YTkl0eM8&us=0&ori=1&bf=4&ot=v&lp=0000fND37&ps=mZ6WB&uid=85KfK1&ab=,15568-g4,8012-g2,8013-g0,3601-g38&Expires=1761707830&ssig=B6zrptVG2k&KID=unistore,video"
        }
      },
      "score": 22.599999999999998
    },
    {
      "id": "detail-6197418994158952393",
      "bid": null,
      "url": "https://weibo.com/3138996784/QbkEztSBY?refer_flag=1001030103_",
      "created_at": "今天09:02",
      "user_id": null,
      "user_name": "珍石部落",
      "verified": null,
      "region": null,
      "source": "",
      "text": "#被蛇咬后失联的网红已找到#阿弥陀佛--没事就好！医院猛于毒蛇！ ​",
      "text_raw": "#被蛇咬后失联的网红已找到#阿弥陀佛--没事就好！医院猛于毒蛇！ ​",
      "reposts": 0,
      "comments": 3,
      "likes": 16,
      "pics": [
        "https://tvax4.sinaimg.cn/crop.0.0.750.750.180/0085KfK1ly8h540v278acj30ku0kuzkp.jpg?KID=imgbed,tva&Expires=1761715030&ssig=lGAJiygakH",
        "https://tvax3.sinaimg.cn/crop.0.0.1080.1080.180/bb194a30ly8hjllih3dnvj20u00u1n0b.jpg?KID=imgbed,tva&Expires=1761715030&ssig=TyaiN1Wzsl",
        "https://h5.sinaimg.cn/upload/108/1866/2022/11/02/vvip_2.png",
        "https://wx3.sinaimg.cn/orj360/bb194a30gy1i6syx74zf0j20gv0aidjj.jpg",
        "https://tva1.sinaimg.cn/default/images/default_avatar_male_180.gif",
        "https://a.sinaimg.cn/mintra/pic/2201190827/32aria.png"
      ],
      "video": null,
      "score": 2.5
    },
    {
      "id": "detail-8284201315937741145",
      "bid": null,
      "url": "https://weibo.com/1744332207/Qbk6E3zEc?refer_flag=1001030103_",
      "created_at": "今天07:39",
      "user_id": null,
      "user_name": "钱江视频",
      "verified": null,
      "region": null,
      "source": "",
      "text": "【当地居民称#被蛇咬失联网红看到救援队后弃车#有网友质疑其为“演戏”】#被蛇咬后失联的网红已找到#10月27日，据报道，湖南邵阳洞口县一名男子尹华健在直播挖蛇时被银环蛇咬伤，他到医院检查后嫌血清贵自行离开，随后失联。这两天内，当地的公安机关、救援力量进行了大规模搜救，仍未找到该男 ​展开c",
      "text_raw": "【当地居民称#被蛇咬失联网红看到救援队后弃车#有网友质疑其为“演戏”】#被蛇咬后失联的网红已找到#10月27日，据报道，湖南邵阳洞口县一名男子尹华健在直播挖蛇时被银环蛇咬伤，他到医院检查后嫌血清贵自行离开，随后失联。这两天内，当地的公安机关、救援力量进行了大规模搜救，仍未找到该男 ​展开c",
      "reposts": 119,
      "comments": 13,
      "likes": 59,
      "pics": [
        "https://tvax4.sinaimg.cn/crop.0.0.750.750.180/0085KfK1ly8h540v278acj30ku0kuzkp.jpg?KID=imgbed,tva&Expires=1761715030&ssig=lGAJiygakH",
        "https://tvax3.sinaimg.cn/crop.0.0.512.512.180/67f865afly8h8vg6w30czj20e80e8t92.jpg?KID=imgbed,tva&Expires=1761715030&ssig=fiPH2RkMOW",
        "https://h5.sinaimg.cn/upload/108/1866/2022/11/02/vvip_2.png",
        "https://d.sinaimg.cn/prd/100/18/2025/03/29/timeline_earth_old_default.png",
        "https://h5.sinaimg.cn/upload/2015/09/25/3/timeline_card_small_video_default.png",
        "https://tvax3.sinaimg.cn/crop.0.0.512.512.1024/67f865afly8h8vg6w30czj20e80e8t92.jpg?KID=imgbed,tva&Expires=1761715030&ssig=0f%2FMw2s7bF",
        "https://tva1.sinaimg.cn/default/images/default_avatar_male_180.gif",
        "https://a.sinaimg.cn/mintra/pic/2201190827/32aria.png"
      ],
      "video": {
        "title": null,
        "cover": null,
        "duration": null,
        "streams": {
          "stream_url": "https://f.video.weibocdn.com/o0/pZBuZUQElx08syeP3mtO010412005JSj0E010.mp4?label=mp4_720p&template=720x1280.24.0&media_id=5226988697223174&tp=8x8A3El:YTkl0eM8&us=0&ori=1&bf=4&ot=v&lp=0000fND37&ps=mZ6WB&uid=85KfK1&ab=,15568-g4,3601-g43,8013-g0,3601-g36&Expires=1761707830&ssig=QH2EgfnFR1&KID=unistore,video"
        }
      },
      "score": 81.2
    },
    {
      "id": "detail-7708163158179036931",
      "bid": null,
      "url": "https://weibo.com/1700087532/QbeXU5d3o?refer_flag=1001030103_",
      "created_at": "10月28日 18:33",
      "user_id": null,
      "user_name": "三湘都市报",
      "verified": null,
      "region": null,
      "source": "",
      "text": "【#被蛇咬后失联的网红的车辆已找到#】#救援人员连续两天搜救疑被蛇咬网红#10月27日，有网友发视频称，湖南邵阳洞口县有一名男子尹华健在直播挖蛇时被蛇咬伤，他到医院检查后嫌血清贵自行离开，至今下落不明。如今两天过去，当地的公安机关、救援力量经过大规模搜救，仍未有尹华健的消息。10月28日下 ​展开c",
      "text_raw": "【#被蛇咬后失联的网红的车辆已找到#】#救援人员连续两天搜救疑被蛇咬网红#10月27日，有网友发视频称，湖南邵阳洞口县有一名男子尹华健在直播挖蛇时被蛇咬伤，他到医院检查后嫌血清贵自行离开，至今下落不明。如今两天过去，当地的公安机关、救援力量经过大规模搜救，仍未有尹华健的消息。10月28日下 ​展开c",
      "reposts": 4,
      "comments": 4,
      "likes": 24,
      "pics": [
        "https://tvax4.sinaimg.cn/crop.0.0.750.750.180/0085KfK1ly8h540v278acj30ku0kuzkp.jpg?KID=imgbed,tva&Expires=1761715031&ssig=xjhkaIpaQj",
        "https://tvax1.sinaimg.cn/crop.0.0.179.179.180/001R3oqEly8h8vg5q4wzdj604z04z3yf02.jpg?KID=imgbed,tva&Expires=1761715032&ssig=c6dTsMU%2F8U",
        "https://h5.sinaimg.cn/upload/108/1866/2022/11/02/vvip_2.png",
        "https://h5.sinaimg.cn/upload/2015/09/25/3/timeline_card_small_video_default.png",
        "https://tvax1.sinaimg.cn/crop.0.0.179.179.1024/001R3oqEly8h8vg5q4wzdj604z04z3yf02.jpg?KID=imgbed,tva&Expires=1761715032&ssig=skCxybGi7e",
        "https://wx1.sinaimg.cn/mw690/001R3oqEgy1h5i0re2ak6j60km0g7n0k02.jpg",
        "https://a.sinaimg.cn/mintra/pic/2201190827/32aria.png"
      ],
      "video": {
        "title": null,
        "cover": null,
        "duration": null,
        "streams": {
          "stream_url": "https://f.video.weibocdn.com/o0/MpcucvWblx08sxpZrVji010412006d5I0E010.mp4?label=mp4_720p&template=720x1280.24.0&media_id=5226802650742920&tp=8x8A3El:YTkl0eM8&us=0&ori=1&bf=4&ot=v&lp=0000fND37&ps=mZ6WB&uid=85KfK1&ab=,15568-g4,8012-g2,3601-g43,8013-g0,3601-g36&Expires=1761707832&ssig=701PX4tGx%2B&KID=unistore,video"
        }
      },
      "score": 6.0
    },
    {
      "id": "detail-3622014769812195994",
      "bid": null,
      "url": "https://weibo.com/1655444627/QbhfLEOlc?refer_flag=1001030103_",
      "created_at": "今天00:23",
      "user_id": null,
      "user_name": "潇湘晨报",
      "verified": null,
      "region": null,
      "source": "",
      "text": "【#直播抓银环蛇被咬伤网红已回家#】#家属回应网红抓蛇被咬伤质疑为炒作#10月27日，湖南邵阳，有网友发视频称，男子尹某某在直播捉蛇过程中被咬伤，送医后却因费用问题自行离开，随后失联。28日晚，据记者采访，值班医生称“被蛇咬伤”只是来源于尹某某的口述，并未进行检查，问询期间尹某某曾改口为“ ​展开c",
      "text_raw": "【#直播抓银环蛇被咬伤网红已回家#】#家属回应网红抓蛇被咬伤质疑为炒作#10月27日，湖南邵阳，有网友发视频称，男子尹某某在直播捉蛇过程中被咬伤，送医后却因费用问题自行离开，随后失联。28日晚，据记者采访，值班医生称“被蛇咬伤”只是来源于尹某某的口述，并未进行检查，问询期间尹某某曾改口为“ ​展开c",
      "reposts": 2,
      "comments": 9,
      "likes": 96,
      "pics": [
        "https://tvax4.sinaimg.cn/crop.0.0.750.750.180/0085KfK1ly8h540v278acj30ku0kuzkp.jpg?KID=imgbed,tva&Expires=1761715031&ssig=xjhkaIpaQj",
        "https://tvax4.sinaimg.cn/crop.0.0.826.826.180/001O24LNly8h8viu4nck1j60my0myq3m02.jpg?KID=imgbed,tva&Expires=1761715032&ssig=i20iu2T8XF",
        "https://h5.sinaimg.cn/upload/108/1866/2022/11/02/vvip_3.png",
        "https://h5.sinaimg.cn/upload/2015/09/25/3/timeline_card_small_video_default.png",
        "https://tvax4.sinaimg.cn/crop.0.0.826.826.1024/001O24LNly8h8viu4nck1j60my0myq3m02.jpg?KID=imgbed,tva&Expires=1761715032&ssig=SnHkM9VXsg",
        "https://tva1.sinaimg.cn/default/images/default_avatar_male_180.gif",
        "https://a.sinaimg.cn/mintra/pic/2201190827/32aria.png"
      ],
      "video": {
        "title": null,
        "cover": null,
        "duration": null,
        "streams": {
          "stream_url": "https://f.video.weibocdn.com/o0/1zWKx5cblx08sxKUjDa0010412006Ke30E010.mp4?label=mp4_720p&template=720x1280.24.0&media_id=5226869793161256&tp=8x8A3El:YTkl0eM8&us=0&ori=1&bf=4&ot=v&lp=0000fND37&ps=mZ6WB&uid=85KfK1&ab=,15568-g4,3601-g43,8013-g0,3601-g36&Expires=1761707832&ssig=7oAGeUHqUC&KID=unistore,video"
        }
      },
      "score": 13.5
    },
    {
      "id": "detail-1500377259961457654",
      "bid": null,
      "url": "https://weibo.com/1642512402/Qbkzccdvu?refer_flag=1001030103_",
      "created_at": "今天08:49",
      "user_id": null,
      "user_name": "中国新闻周刊",
      "verified": null,
      "region": null,
      "source": "",
      "text": "【#网红称被蛇咬伤离开医院后用草药治疗#】#网红称被蛇咬后手指已变形#10月28日，记者赶赴邵阳洞口，追踪“网红直播抓蛇被咬伤后开车失联”事件。晚上11点左右，在记者结束直播后不久，当事人尹华健用家人的手机号码联系到记者，告知其已经回到家中，与家人团聚了。尹华健表示，因为自己和毒蛇打交 ​展开c",
      "text_raw": "【#网红称被蛇咬伤离开医院后用草药治疗#】#网红称被蛇咬后手指已变形#10月28日，记者赶赴邵阳洞口，追踪“网红直播抓蛇被咬伤后开车失联”事件。晚上11点左右，在记者结束直播后不久，当事人尹华健用家人的手机号码联系到记者，告知其已经回到家中，与家人团聚了。尹华健表示，因为自己和毒蛇打交 ​展开c",
      "reposts": 1,
      "comments": 7,
      "likes": 13,
      "pics": [
        "https://tvax4.sinaimg.cn/crop.0.0.750.750.180/0085KfK1ly8h540v278acj30ku0kuzkp.jpg?KID=imgbed,tva&Expires=1761715031&ssig=xjhkaIpaQj",
        "https://tvax2.sinaimg.cn/crop.0.0.1080.1080.180/001N9Ovwly8h8vgj46gr1j60u00u03zp02.jpg?KID=imgbed,tva&Expires=1761715032&ssig=p%2FM%2BHTTK7o",
        "https://h5.sinaimg.cn/upload/108/1866/2022/11/02/vvip_2.png",
        "https://h5.sinaimg.cn/upload/2015/09/25/3/timeline_card_small_video_default.png",
        "https://wx3.sinaimg.cn/orj480/001N9Ovwly1i6syjea6apj60k00zkwg102.jpg",
        "https://tva1.sinaimg.cn/default/images/default_avatar_male_180.gif",
        "https://a.sinaimg.cn/mintra/pic/2201190827/32aria.png"
      ],
      "video": null,
      "score": 4.0
    }
  ]
}