{
  "topic": "#第一观察#",
  "fetched_at": "2025-10-28T20:55:25+08:00",
  "total": 20,
  "top_n": 30,
  "items": [
    {
      "id": "detail-9013675584019756018",
      "bid": null,
      "url": "https://weibo.com/1699432410/Qb7wR7Dva?refer_flag=1001030103_",
      "created_at": "10月27日 23:38",
      "user_id": null,
      "user_name": "新华社",
      "verified": null,
      "region": null,
      "source": "",
      "text": "【#第一观察#| 锚定目标 团结奋进】是什么，让14亿多人的脚步坚定向前？有外国领导人对习近平总书记说：“中国有一大优势，你们总是制定各种规划，而且各种规划总是能实现。”五年，1800多天，4万多小时。中国用一个个五年，把不可能变成可能，把蓝图变成现实。“十五五”将是一个怎样的五年？将是一 ​展开c",
      "text_raw": "【#第一观察#| 锚定目标 团结奋进】是什么，让14亿多人的脚步坚定向前？有外国领导人对习近平总书记说：“中国有一大优势，你们总是制定各种规划，而且各种规划总是能实现。”五年，1800多天，4万多小时。中国用一个个五年，把不可能变成可能，把蓝图变成现实。“十五五”将是一个怎样的五年？将是一 ​展开c",
      "reposts": 113,
      "comments": 87,
      "likes": 427,
      "pics": [
        "https://tvax4.sinaimg.cn/crop.0.0.750.750.180/0085KfK1ly8h540v278acj30ku0kuzkp.jpg?KID=imgbed,tva&Expires=1761666917&ssig=GeQKouv76%2B",
        "https://tvax2.sinaimg.cn/crop.58.61.875.875.180/001R0E0aly8h8vg6xx3srj60rs0rsdko02.jpg?KID=imgbed,tva&Expires=1761666917&ssig=7oVLRbKbEb",
        "https://h5.sinaimg.cn/upload/108/1866/2022/11/02/vvip_4.png",
        "https://h5.sinaimg.cn/upload/2015/09/25/3/timeline_card_small_video_default.png",
        "https://tvax2.sinaimg.cn/crop.58.61.875.875.1024/001R0E0aly8h8vg6xx3srj60rs0rsdko02.jpg?KID=imgbed,tva&Expires=1761666917&ssig=s0NFAZpsbU",
        "https://tva1.sinaimg.cn/default/images/default_avatar_male_180.gif",
        "https://a.sinaimg.cn/mintra/pic/2201190827/32aria.png"
      ],
      "video": {
        "title": null,
        "cover": null,
        "duration": null,
        "streams": {
          "stream_url": "https://f.video.weibocdn.com/o0/3pGRJ8c8lx08sw6VZkdy010412027MoQ0E010.mp4?label=mp4_720p&template=720x1280.24.0&media_id=5226501550047312&tp=8x8A3El:YTkl0eM8&us=0&ori=1&bf=4&ot=v&lp=0000fND37&ps=mZ6WB&uid=85KfK1&ab=,15568-g4,8013-g0,3601-g38&Expires=1761659717&ssig=ex3GHrZpZF&KID=unistore,video"
        }
      },
      "score": 136.6
    },
    {
      "id": "detail-4329115454457104593",
      "bid": null,
      "url": "https://weibo.com/3309826382/QbenokjZN?refer_flag=1001030103_",
      "created_at": "今天17:04",
      "user_id": null,
      "user_name": "健康成都官微",
      "verified": null,
      "region": null,
      "source": "",
      "text": "#小卫爱分享#【脆皮山药】百分之九十九的人都吃过山药，但这个做法很多人都不知道，外酥里软，大人小孩都爱吃。（美食翁）L美食翁的微博视频#第一观察#​",
      "text_raw": "#小卫爱分享#【脆皮山药】百分之九十九的人都吃过山药，但这个做法很多人都不知道，外酥里软，大人小孩都爱吃。（美食翁）L美食翁的微博视频#第一观察#​",
      "reposts": 3,
      "comments": 166,
      "likes": 31,
      "pics": [
        "https://tvax4.sinaimg.cn/crop.0.0.750.750.180/0085KfK1ly8h540v278acj30ku0kuzkp.jpg?KID=imgbed,tva&Expires=1761666917&ssig=GeQKouv76%2B",
        "https://tvax1.sinaimg.cn/crop.0.0.996.996.180/c547f14ely8gvx1d0zh92j20ro0roadp.jpg?KID=imgbed,tva&Expires=1761666918&ssig=VlDI%2F8mWd5",
        "https://h5.sinaimg.cn/upload/108/1866/2022/11/02/vvip_1.png",
        "https://h5.sinaimg.cn/upload/2015/09/25/3/timeline_card_small_video_default.png",
        "https://tvax2.sinaimg.cn/crop.0.0.512.512.1024/4be8e357ly8fsfb6l5s8jj20e80e8mxk.jpg?KID=imgbed,tva&Expires=1761666918&ssig=EAsPy8lnVr",
        "https://tva1.sinaimg.cn/default/images/default_avatar_male_180.gif",
        "https://a.sinaimg.cn/mintra/pic/2201190827/32aria.png"
      ],
      "video": {
        "title": null,
        "cover": null,
        "duration": null,
        "streams": {
          "stream_url": "https://f.video.weibocdn.com/o0/W2z1RMqIlx08sbjRqZsI01041200okaf0E010.mp4?label=mp4_720p&template=720x1280.24.0&media_id=5221781263548491&tp=8x8A3El:YTkl0eM8&us=0&ori=1&bf=4&ot=v&lp=0000fND37&ps=mZ6WB&uid=85KfK1&ab=,15568-g4,8012-g2,3601-g43,8013-g0,3601-g41,3601-g36&Expires=1761659718&ssig=72z2Z4z%2BgL&KID=unistore,video"
        }
      },
      "score": 54.699999999999996
    },
    {
      "id": "detail-7494556172849532473",
      "bid": null,
      "url": "https://weibo.com/3309826382/QbeZ8C0nk?refer_flag=1001030103_",
      "created_at": "今天18:37",
      "user_id": null,
      "user_name": "健康成都官微",
      "verified": null,
      "region": null,
      "source": "",
      "text": "#健康科普课堂#【#年轻不穿秋裤老了会得关节炎吗#】#降温不穿秋裤会不会冻出关节炎#关节炎，顾名思义，就是发生于关节部位的炎症，典型表现为关节部位的疼痛、肿胀、活动受限。关节炎患者的滑膜组织存在炎性病变，受到大风、降温等外界刺激时，炎性因子聚集、关节积液，会加重关节疼痛、肿 ​展开c",
      "text_raw": "#健康科普课堂#【#年轻不穿秋裤老了会得关节炎吗#】#降温不穿秋裤会不会冻出关节炎#关节炎，顾名思义，就是发生于关节部位的炎症，典型表现为关节部位的疼痛、肿胀、活动受限。关节炎患者的滑膜组织存在炎性病变，受到大风、降温等外界刺激时，炎性因子聚集、关节积液，会加重关节疼痛、肿 ​展开c",
      "reposts": 2,
      "comments": 97,
      "likes": 12,
      "pics": [
        "https://tvax4.sinaimg.cn/crop.0.0.750.750.180/0085KfK1ly8h540v278acj30ku0kuzkp.jpg?KID=imgbed,tva&Expires=1761666917&ssig=GeQKouv76%2B",
        "https://tvax1.sinaimg.cn/crop.0.0.996.996.180/c547f14ely8gvx1d0zh92j20ro0roadp.jpg?KID=imgbed,tva&Expires=1761666918&ssig=VlDI%2F8mWd5",
        "https://h5.sinaimg.cn/upload/108/1866/2022/11/02/vvip_1.png",
        "https://h5.sinaimg.cn/upload/2015/09/25/3/timeline_card_small_video_default.png",
        "https://tvax3.sinaimg.cn/crop.0.0.512.512.1024/001W3LkXly8h8w4pp4azmj60e80e8q3b02.jpg?KID=imgbed,tva&Expires=1761666918&ssig=6qon76znVn",
        "https://wx4.sinaimg.cn/mw690/a1d3feably1fl9nr80k11j20hs0hsmze.jpg",
        "https://a.sinaimg.cn/mintra/pic/2201190827/32aria.png"
      ],
      "video": {
        "title": null,
        "cover": null,
        "duration": null,
        "streams": {
          "stream_url": "https://f.video.weibocdn.com/o0/HOdPhmlTlx08sdYUkHdK010412002uWB0E010.mp4?label=mp4_720p&template=720x1280.24.0&media_id=5222385696047181&tp=8x8A3El:YTkl0eM8&us=0&ori=1&bf=4&ot=v&lp=0000fND37&ps=mZ6WB&uid=85KfK1&ab=,15568-g4,3601-g43,8013-g0,3601-g38&Expires=1761659718&ssig=xiSxGHwm2Z&KID=unistore,video"
        }
      },
      "score": 31.499999999999996
    },
    {
      "id": "detail-7297130218136366834",
      "bid": null,
      "url": "https://weibo.com/7748069363/QbfMn38JI?refer_flag=1001030103_",
      "created_at": "16分钟前",
      "user_id": null,
      "user_name": "首都老兵",
      "verified": null,
      "region": null,
      "source": "",
      "text": "#时政小课堂#“十五五”时期，战略任务和重大举措有哪些？快戳图了解↓ 未来五年，一起加油干！（央视新闻）​#第一观察##首都老兵#​",
      "text_raw": "#时政小课堂#“十五五”时期，战略任务和重大举措有哪些？快戳图了解↓ 未来五年，一起加油干！（央视新闻）​#第一观察##首都老兵#​",
      "reposts": 0,
      "comments": 0,
      "likes": 3,
      "pics": [
        "https://tvax4.sinaimg.cn/crop.0.0.750.750.180/0085KfK1ly8h540v278acj30ku0kuzkp.jpg?KID=imgbed,tva&Expires=1761666917&ssig=GeQKouv76%2B",
        "https://tvax1.sinaimg.cn/crop.0.0.600.600.180/008sm6MHly8hkbr1zf7rtj30go0gomzn.jpg?KID=imgbed,tva&Expires=1761666918&ssig=T6sujf54XH",
        "https://h5.sinaimg.cn/upload/108/1866/2022/11/02/vvip_1.png",
        "https://wx3.sinaimg.cn/orj360/008sm6MHly1i6sdeevg8qj30rvbf0hdv.jpg",
        "https://a.sinaimg.cn/mintra/pic/2201190827/32aria.png"
      ],
      "video": null,
      "score": 0.30000000000000004
    },
    {
      "id": "detail-1989924467480192119",
      "bid": null,
      "url": "https://weibo.com/2634384567/Qbfb6cEfW?refer_flag=1001030103_",
      "created_at": "今天19:06",
      "user_id": null,
      "user_name": "河北发布",
      "verified": null,
      "region": null,
      "source": "",
      "text": "#河北阜平华北豹影像首度公开#【确认了！#河北阜平已观测到3只华北豹#】日前，河北银河山省级自然保护区连续发现华北豹的新闻引发网友关注。经@河北发布与清华大学建筑学院景观学系教师王沛确认，自2024年4月起，在保护区内布设的红外相机多次捕捉到国家一级保护动物华北豹的清晰影像，一年多来已观测 ​展开c",
      "text_raw": "#河北阜平华北豹影像首度公开#【确认了！#河北阜平已观测到3只华北豹#】日前，河北银河山省级自然保护区连续发现华北豹的新闻引发网友关注。经@河北发布与清华大学建筑学院景观学系教师王沛确认，自2024年4月起，在保护区内布设的红外相机多次捕捉到国家一级保护动物华北豹的清晰影像，一年多来已观测 ​展开c",
      "reposts": 4,
      "comments": 5,
      "likes": 50,
      "pics": [
        "https://tvax4.sinaimg.cn/crop.0.0.750.750.180/0085KfK1ly8h540v278acj30ku0kuzkp.jpg?KID=imgbed,tva&Expires=1761666918&ssig=e%2Fp%2Fb1PuW3",
        "https://tvax2.sinaimg.cn/crop.0.0.600.600.180/002ShBLFly8i577x43npxj60go0go40302.jpg?KID=imgbed,tva&Expires=1761666919&ssig=ftioOd9C0N",
        "https://h5.sinaimg.cn/upload/108/1866/2022/11/02/vip_2.png",
        "https://h5.sinaimg.cn/upload/2015/09/25/3/timeline_card_small_video_default.png",
        "https://tvax2.sinaimg.cn/crop.0.0.600.600.1024/002ShBLFly8i577x43npxj60go0go40302.jpg?KID=imgbed,tva&Expires=1761666919&ssig=soWwBabuGi",
        "https://ww1.sinaimg.cn/mw690/549d0121tw1egm1kjly3jj20hs0hsq4f.jpg",
        "https://a.sinaimg.cn/mintra/pic/2201190827/32aria.png"
      ],
      "video": {
        "title": null,
        "cover": null,
        "duration": null,
        "streams": {
          "stream_url": "https://f.video.weibocdn.com/o0/IoNdDqRVlx08sxpbhaHK01041200ASw70E010.mp4?label=mp4_720p&template=720x1280.24.0&media_id=5226798129020938&tp=8x8A3El:YTkl0eM8&us=0&ori=1&bf=4&ot=v&lp=0000fND37&ps=mZ6WB&uid=85KfK1&ab=,15568-g4,3601-g43,8013-g0&Expires=1761659719&ssig=3X9VWofjKr&KID=unistore,video"
        }
      },
      "score": 8.9
    },
    {
      "id": "detail-7005468740656205787",
      "bid": null,
      "url": "https://weibo.com/3888907806/Qbarm7SEN?refer_flag=1001030103_",
      "created_at": "今天07:02",
      "user_id": null,
      "user_name": "三门峡日报",
      "verified": null,
      "region": null,
      "source": "",
      "text": "【#第一观察#| 锚定目标 团结奋进】是什么，让14亿多人的脚步坚定向前？有外国领导人对习近平总书记说：“中国有一大优势，你们总是制定各种规划，而且各种规划总是能实现。”五年，1800多天，4万多小时。中国用一个个五年，把不可能变成可能，把蓝图变成现实。“十五五”将是一个怎样的五年？将是一 ​展开c",
      "text_raw": "【#第一观察#| 锚定目标 团结奋进】是什么，让14亿多人的脚步坚定向前？有外国领导人对习近平总书记说：“中国有一大优势，你们总是制定各种规划，而且各种规划总是能实现。”五年，1800多天，4万多小时。中国用一个个五年，把不可能变成可能，把蓝图变成现实。“十五五”将是一个怎样的五年？将是一 ​展开c",
      "reposts": 2,
      "comments": 5,
      "likes": 9,
      "pics": [
        "https://tvax4.sinaimg.cn/crop.0.0.750.750.180/0085KfK1ly8h540v278acj30ku0kuzkp.jpg?KID=imgbed,tva&Expires=1761666918&ssig=e%2Fp%2Fb1PuW3",
        "https://tvax1.sinaimg.cn/crop.0.0.690.690.180/e7cc061ely8h8w37yioxaj20j60j6aae.jpg?KID=imgbed,tva&Expires=1761666919&ssig=vf2ZDtK24z",
        "https://h5.sinaimg.cn/upload/108/1866/2022/11/02/vip_6.png",
        "https://h5.sinaimg.cn/upload/2015/09/25/3/timeline_card_small_video_default.png",
        "https://tvax2.sinaimg.cn/crop.58.61.875.875.1024/001R0E0aly8h8vg6xx3srj60rs0rsdko02.jpg?KID=imgbed,tva&Expires=1761666919&ssig=BwFjZgsUvY",
        "https://tva1.sinaimg.cn/default/images/default_avatar_male_180.gif",
        "https://a.sinaimg.cn/mintra/pic/2201190827/32aria.png"
      ],
      "video": {
        "title": null,
        "cover": null,
        "duration": null,
        "streams": {
          "stream_url": "https://f.video.weibocdn.com/o0/3pGRJ8c8lx08sw6VZkdy010412027MoQ0E010.mp4?label=mp4_720p&template=720x1280.24.0&media_id=5226501550047312&tp=8x8A3El:YTkl0eM8&us=0&ori=1&bf=4&ot=v&lp=0000fND37&ps=mZ6WB&uid=85KfK1&ab=,15568-g4,8013-g0,3601-g38&Expires=1761659719&ssig=4QtZk0mjwz&KID=unistore,video"
        }
      },
      "score": 3.6
    },
    {
      "id": "detail-3168796614380057438",
      "bid": null,
      "url": "https://weibo.com/2685336121/Qb7G647DN?refer_flag=1001030103_",
      "created_at": "今天00:00",
      "user_id": null,
      "user_name": "南宁晚报",
      "verified": null,
      "region": null,
      "source": "",
      "text": "【#第一观察#| 锚定目标 团结奋进】是什么，让14亿多人的脚步坚定向前？有外国领导人对习近平总书记说：“中国有一大优势，你们总是制定各种规划，而且各种规划总是能实现。”五年，1800多天，4万多小时。中国用一个个五年，把不可能变成可能，把蓝图变成现实。“十五五”将是一个怎样的五年？将是一 ​展开c",
      "text_raw": "【#第一观察#| 锚定目标 团结奋进】是什么，让14亿多人的脚步坚定向前？有外国领导人对习近平总书记说：“中国有一大优势，你们总是制定各种规划，而且各种规划总是能实现。”五年，1800多天，4万多小时。中国用一个个五年，把不可能变成可能，把蓝图变成现实。“十五五”将是一个怎样的五年？将是一 ​展开c",
      "reposts": 11,
      "comments": 14,
      "likes": 18,
      "pics": [
        "https://tvax4.sinaimg.cn/crop.0.0.750.750.180/0085KfK1ly8h540v278acj30ku0kuzkp.jpg?KID=imgbed,tva&Expires=1761666918&ssig=e%2Fp%2Fb1PuW3",
        "https://tvax3.sinaimg.cn/crop.0.0.1080.1080.180/a00efa39ly8h8vg6v5d0xj20u00u0761.jpg?KID=imgbed,tva&Expires=1761666919&ssig=1ohI5AtyaR",
        "https://h5.sinaimg.cn/upload/108/1866/2022/11/02/vvip_1.png",
        "https://h5.sinaimg.cn/upload/2015/09/25/3/timeline_card_small_video_default.png",
        "https://tvax2.sinaimg.cn/crop.58.61.875.875.1024/001R0E0aly8h8vg6xx3srj60rs0rsdko02.jpg?KID=imgbed,tva&Expires=1761666919&ssig=BwFjZgsUvY",
        "https://tva1.sinaimg.cn/default/images/default_avatar_male_180.gif",
        "https://a.sinaimg.cn/mintra/pic/2201190827/32aria.png"
      ],
      "video": {
        "title": null,
        "cover": null,
        "duration": null,
        "streams": {
          "stream_url": "https://f.video.weibocdn.com/o0/3pGRJ8c8lx08sw6VZkdy010412027MoQ0E010.mp4?label=mp4_720p&template=720x1280.24.0&media_id=5226501550047312&tp=8x8A3El:YTkl0eM8&us=0&ori=1&bf=4&ot=v&lp=0000fND37&ps=mZ6WB&uid=85KfK1&ab=,15568-g4,8013-g0,3601-g38&Expires=1761659719&ssig=4QtZk0mjwz&KID=unistore,video"
        }
      },
      "score": 12.600000000000001
    },
    {
      "id": "detail-3495848941659786198",
      "bid": null,
      "url": "https://weibo.com/1699432410/Qaw0ciV8w?refer_flag=1001030103_",
      "created_at": "10月24日 00:06",
      "user_id": null,
      "user_name": "新华社",
      "verified": null,
      "region": null,
      "source": "",
      "text": "【#第一观察#| 关键时期的关键部署】党的二十届四中全会，审议通过了《中共中央关于制定国民经济和社会发展第十五个五年规划的建议》。这是新时代以来党中央制定的第三个五年规划建议，也是全面建设社会主义现代化国家新征程上的第一个五年规划建议。详情请看↓O第一观察｜关键时期的关键部署​",
      "text_raw": "【#第一观察#| 关键时期的关键部署】党的二十届四中全会，审议通过了《中共中央关于制定国民经济和社会发展第十五个五年规划的建议》。这是新时代以来党中央制定的第三个五年规划建议，也是全面建设社会主义现代化国家新征程上的第一个五年规划建议。详情请看↓O第一观察｜关键时期的关键部署​",
      "reposts": 81,
      "comments": 7,
      "likes": 194,
      "pics": [
        "https://tvax4.sinaimg.cn/crop.0.0.750.750.180/0085KfK1ly8h540v278acj30ku0kuzkp.jpg?KID=imgbed,tva&Expires=1761666919&ssig=07ESgMLDGz",
        "https://tvax2.sinaimg.cn/crop.58.61.875.875.180/001R0E0aly8h8vg6xx3srj60rs0rsdko02.jpg?KID=imgbed,tva&Expires=1761666919&ssig=JfJPOh4EfZ",
        "https://h5.sinaimg.cn/upload/108/1866/2022/11/02/vvip_4.png",
        "https://wx4.sinaimg.cn/large/001R0E0aly1i6mr89y0d3j60rs0fmadk02.jpg",
        "https://h5.sinaimg.cn/upload/2016/12/28/14/feed_headlines_icon_flash20161228_3.png",
        "https://tva1.sinaimg.cn/default/images/default_avatar_male_180.gif",
        "https://a.sinaimg.cn/mintra/pic/2201190827/32aria.png"
      ],
      "video": null,
      "score": 70.10000000000001
    },
    {
      "id": "detail-3005596666274219518",
      "bid": null,
      "url": "https://weibo.com/1699432410/Q9rxHcAXu?refer_flag=1001030103_",
      "created_at": "10月16日 22:54",
      "user_id": null,
      "user_name": "新华社",
      "verified": null,
      "region": null,
      "source": "",
      "text": "【#第一观察#| 维护世界粮食安全的中国行动】在10月16日世界粮食日这天，习近平总书记向联合国粮食及农业组织成立80周年致贺信，强调中国政府高度重视粮食安全，坚持依靠自身解决好14亿多人口的吃饭问题，并向有需要的国家提供力所能及的帮助，为保障世界粮食安全贡献了中国力量。对维护全球粮食安全 ​展开c",
      "text_raw": "【#第一观察#| 维护世界粮食安全的中国行动】在10月16日世界粮食日这天，习近平总书记向联合国粮食及农业组织成立80周年致贺信，强调中国政府高度重视粮食安全，坚持依靠自身解决好14亿多人口的吃饭问题，并向有需要的国家提供力所能及的帮助，为保障世界粮食安全贡献了中国力量。对维护全球粮食安全 ​展开c",
      "reposts": 69,
      "comments": 63,
      "likes": 295,
      "pics": [
        "https://tvax4.sinaimg.cn/crop.0.0.750.750.180/0085KfK1ly8h540v278acj30ku0kuzkp.jpg?KID=imgbed,tva&Expires=1761666919&ssig=07ESgMLDGz",
        "https://tvax2.sinaimg.cn/crop.58.61.875.875.180/001R0E0aly8h8vg6xx3srj60rs0rsdko02.jpg?KID=imgbed,tva&Expires=1761666920&ssig=NfRPW6%2BHsV",
        "https://h5.sinaimg.cn/upload/108/1866/2022/11/02/vvip_4.png",
        "https://wx4.sinaimg.cn/large/001R0E0aly1i6el6v36efj60rs0fmdjc02.jpg",
        "https://h5.sinaimg.cn/upload/2016/12/28/14/feed_headlines_icon_flash20161228_3.png",
        "https://tva1.sinaimg.cn/default/images/default_avatar_male_180.gif",
        "https://a.sinaimg.cn/mintra/pic/2201190827/32aria.png"
      ],
      "video": null,
      "score": 89.8
    },
    {
      "id": "detail-4947268642579985238",
      "bid": null,
      "url": "https://weibo.com/6890796357/Q9uRXd8OZ?refer_flag=1001030103_",
      "created_at": "10月17日 07:22",
      "user_id": null,
      "user_name": "日照日报",
      "verified": null,
      "region": null,
      "source": "",
      "text": "【#第一观察#| 维护世界粮食安全的中国行动】在10月16日世界粮食日这天，习近平总书记向联合国粮食及农业组织成立80周年致贺信，强调中国政府高度重视粮食安全，坚持依靠自身解决好14亿多人口的吃饭问题，并向有需要的国家提供力所能及的帮助，为保障世界粮食安全贡献了中国力量。对维护全球粮食安全 ​展开c",
      "text_raw": "【#第一观察#| 维护世界粮食安全的中国行动】在10月16日世界粮食日这天，习近平总书记向联合国粮食及农业组织成立80周年致贺信，强调中国政府高度重视粮食安全，坚持依靠自身解决好14亿多人口的吃饭问题，并向有需要的国家提供力所能及的帮助，为保障世界粮食安全贡献了中国力量。对维护全球粮食安全 ​展开c",
      "reposts": 2,
      "comments": 1,
      "likes": 5,
      "pics": [
        "https://tvax4.sinaimg.cn/crop.0.0.750.750.180/0085KfK1ly8h540v278acj30ku0kuzkp.jpg?KID=imgbed,tva&Expires=1761666919&ssig=07ESgMLDGz",
        "https://tvax3.sinaimg.cn/crop.0.0.1080.1080.180/007wl4UJly8h8vgtpmxmaj30u00u0wfh.jpg?KID=imgbed,tva&Expires=1761666921&ssig=cZWATZ5Het",
        "https://h5.sinaimg.cn/upload/108/1866/2022/11/02/vvip_1.png",
        "https://wx4.sinaimg.cn/large/001R0E0aly1i6el6v36efj60rs0fmdjc02.jpg",
        "https://tvax2.sinaimg.cn/crop.58.61.875.875.180/001R0E0aly8h8vg6xx3srj60rs0rsdko02.jpg?KID=imgbed,tva&Expires=1761666903&ssig=l2l906wWax",
        "https://h5.sinaimg.cn/upload/2016/12/28/14/feed_headlines_icon_flash20161228_3.png",
        "https://tva1.sinaimg.cn/default/images/default_avatar_male_180.gif",
        "https://a.sinaimg.cn/mintra/pic/2201190827/32aria.png"
      ],
      "video": null,
      "score": 2.0
    },
    {
      "id": "detail-2666025686678992701",
      "bid": null,
      "url": "https://weibo.com/2801287904/Q9xxPmxos?refer_flag=1001030103_",
      "created_at": "10月17日 14:11",
      "user_id": null,
      "user_name": "四川监狱",
      "verified": null,
      "region": null,
      "source": "",
      "text": "【#第一观察#| 维护世界粮食安全的中国行动】在10月16日世界粮食日这天，习近平总书记向联合国粮食及农业组织成立80周年致贺信，强调中国政府高度重视粮食安全，坚持依靠自身解决好14亿多人口的吃饭问题，并向有需要的国家提供力所能及的帮助，为保障世界粮食安全贡献了中国力量。对维护全球粮食安全 ​展开c",
      "text_raw": "【#第一观察#| 维护世界粮食安全的中国行动】在10月16日世界粮食日这天，习近平总书记向联合国粮食及农业组织成立80周年致贺信，强调中国政府高度重视粮食安全，坚持依靠自身解决好14亿多人口的吃饭问题，并向有需要的国家提供力所能及的帮助，为保障世界粮食安全贡献了中国力量。对维护全球粮食安全 ​展开c",
      "reposts": 3,
      "comments": 1,
      "likes": 1,
      "pics": [
        "https://tvax4.sinaimg.cn/crop.0.0.750.750.180/0085KfK1ly8h540v278acj30ku0kuzkp.jpg?KID=imgbed,tva&Expires=1761666920&ssig=w4DVvZ2Zse",
        "https://tvax4.sinaimg.cn/crop.0.0.663.663.180/a6f842e0ly8h8vi2szggzj20if0ifq4b.jpg?KID=imgbed,tva&Expires=1761666922&ssig=o0UPnaztoP",
        "https://h5.sinaimg.cn/upload/108/1866/2022/11/02/vvip_1.png",
        "https://wx4.sinaimg.cn/large/001R0E0aly1i6el6v36efj60rs0fmdjc02.jpg",
        "https://tvax2.sinaimg.cn/crop.58.61.875.875.180/001R0E0aly8h8vg6xx3srj60rs0rsdko02.jpg?KID=imgbed,tva&Expires=1761666922&ssig=MneRgqpLoW",
        "https://h5.sinaimg.cn/upload/2016/12/28/14/feed_headlines_icon_flash20161228_3.png",
        "https://tvax2.sinaimg.cn/crop.0.0.382.382.50/006N31MDly8gamw7q4rz0j30am0am1fw.jpg?KID=imgbed,tva&Expires=1761666922&ssig=oof1DyYCHg",
        "https://h5.sinaimg.cn/upload/114/962/2022/07/08/member_0_bigfan3_2.png",
        "https://wx3.sinaimg.cn/mw690/a6f842e0ly1h59k5gbqtrj20qo0qotav.jpg",
        "https://a.sinaimg.cn/mintra/pic/2201190827/32aria.png"
      ],
      "video": null,
      "score": 2.1999999999999997
    },
    {
      "id": "detail-1446125364088351879",
      "bid": null,
      "url": "https://weibo.com/1963894742/Q9vjugzul?refer_flag=1001030103_",
      "created_at": "10月17日 08:30",
      "user_id": null,
      "user_name": "万年融媒",
      "verified": null,
      "region": null,
      "source": "",
      "text": "【#第一观察#| 维护世界粮食安全的中国行动】在10月16日世界粮食日这天，习近平总书记向联合国粮食及农业组织成立80周年致贺信，强调中国政府高度重视粮食安全，坚持依靠自身解决好14亿多人口的吃饭问题，并向有需要的国家提供力所能及的帮助，为保障世界粮食安全贡献了中国力量。对维护全球粮食安全 ​展开c",
      "text_raw": "【#第一观察#| 维护世界粮食安全的中国行动】在10月16日世界粮食日这天，习近平总书记向联合国粮食及农业组织成立80周年致贺信，强调中国政府高度重视粮食安全，坚持依靠自身解决好14亿多人口的吃饭问题，并向有需要的国家提供力所能及的帮助，为保障世界粮食安全贡献了中国力量。对维护全球粮食安全 ​展开c",
      "reposts": 1,
      "comments": 3,
      "likes": 9,
      "pics": [
        "https://tvax4.sinaimg.cn/crop.0.0.750.750.180/0085KfK1ly8h540v278acj30ku0kuzkp.jpg?KID=imgbed,tva&Expires=1761666920&ssig=w4DVvZ2Zse",
        "https://tvax3.sinaimg.cn/crop.0.0.1080.1080.180/750ea7d6ly8i532rby0lyj20u00u0gm8.jpg?KID=imgbed,tva&Expires=1761666922&ssig=QUHblZEhlP",
        "https://wx4.sinaimg.cn/large/001R0E0aly1i6el6v36efj60rs0fmdjc02.jpg",
        "https://tvax2.sinaimg.cn/crop.58.61.875.875.180/001R0E0aly8h8vg6xx3srj60rs0rsdko02.jpg?KID=imgbed,tva&Expires=1761666914&ssig=g685NPZnTV",
        "https://h5.sinaimg.cn/upload/2016/12/28/14/feed_headlines_icon_flash20161228_3.png",
        "https://tvax4.sinaimg.cn/crop.0.0.1080.1080.50/006SQ7HUly8hv3c8447suj30u00u041g.jpg?KID=imgbed,tva&Expires=1761666922&ssig=xMigcCJlH2",
        "https://h5.sinaimg.cn/upload/114/962/2022/07/08/member_0_bigfan1_3.png",
        "https://tvax1.sinaimg.cn/default/images/default_avatar_female_50.gif?KID=imgbed,tva&Expires=1761666922&ssig=Aw3eH%2ByEsc",
        "https://ww1.sinaimg.cn/mw690/549d0121tw1egm1kjly3jj20hs0hsq4f.jpg",
        "https://a.sinaimg.cn/mintra/pic/2201190827/32aria.png"
      ],
      "video": null,
      "score": 2.4
    },
    {
      "id": "detail-7189260055198429085",
      "bid": null,
      "url": "https://weibo.com/1699432410/Q8Zuotb6O?refer_flag=1001030103_",
      "created_at": "10月13日 23:29",
      "user_id": null,
      "user_name": "新华社",
      "verified": null,
      "region": null,
      "source": "",
      "text": "【#第一观察#| 世界妇女事业发展史上新的里程碑】从30年前“以行动谋求平等、发展与和平”，到今天“命运与共：加速妇女全面发展新进程”，北京见证世界妇女事业发展史上新的里程碑。10月13日，习近平主席在北京国家会议中心出席全球妇女峰会开幕式，并发表主旨讲话。详情请看↓O第一观察 | 世界妇女事业发展史上新的里程碑​",
      "text_raw": "【#第一观察#| 世界妇女事业发展史上新的里程碑】从30年前“以行动谋求平等、发展与和平”，到今天“命运与共：加速妇女全面发展新进程”，北京见证世界妇女事业发展史上新的里程碑。10月13日，习近平主席在北京国家会议中心出席全球妇女峰会开幕式，并发表主旨讲话。详情请看↓O第一观察 | 世界妇女事业发展史上新的里程碑​",
      "reposts": 45,
      "comments": 59,
      "likes": 156,
      "pics": [
        "https://tvax4.sinaimg.cn/crop.0.0.750.750.180/0085KfK1ly8h540v278acj30ku0kuzkp.jpg?KID=imgbed,tva&Expires=1761666921&ssig=D9EFLLMPRl",
        "https://tvax2.sinaimg.cn/crop.58.61.875.875.180/001R0E0aly8h8vg6xx3srj60rs0rsdko02.jpg?KID=imgbed,tva&Expires=1761666922&ssig=MneRgqpLoW",
        "https://h5.sinaimg.cn/upload/108/1866/2022/11/02/vvip_4.png",
        "https://wx2.sinaimg.cn/large/001R0E0aly1i6b5wmlwnmj60rs0fmac802.jpg",
        "https://h5.sinaimg.cn/upload/2016/12/28/14/feed_headlines_icon_flash20161228_3.png",
        "https://tvax4.sinaimg.cn/crop.0.0.1080.1080.50/007IIdguly8i6r6fn4rj7j30u00u0q64.jpg?KID=imgbed,tva&Expires=1761666922&ssig=DVKCUJJx70",
        "https://h5.sinaimg.cn/upload/114/962/2022/07/08/member_vvip1_bigfan1_4.png",
        "https://tvax4.sinaimg.cn/crop.0.0.1080.1080.50/006J50C1ly8i6nagnwxukj30u00u0dhe.jpg?KID=imgbed,tva&Expires=1761666922&ssig=wz0jcW9Qui",
        "https://h5.sinaimg.cn/upload/115/735/2022/10/12/svip_8_bigfan3_1.png",
        "https://wx3.sinaimg.cn/mw690/654b47daly1gdik9frqwcj20u00u0n3r.jpg",
        "https://a.sinaimg.cn/mintra/pic/2201190827/32aria.png"
      ],
      "video": null,
      "score": 60.300000000000004
    },
    {
      "id": "detail-3739497351375958900",
      "bid": null,
      "url": "https://weibo.com/1699432410/Q8YXbByDy?refer_flag=1001030103_",
      "created_at": "10月13日 22:07",
      "user_id": null,
      "user_name": "新华社",
      "verified": null,
      "region": null,
      "source": "",
      "text": "【#第一观察#| 肩负起推进妇女事业发展的共同责任】10月13日上午，北京国家会议中心，在全球妇女峰会现场，新华社记者的镜头定格下珍贵瞬间——峰会开始前，国家主席习近平和夫人彭丽媛同与会各国和国际组织代表团团长夫妇合影留念。他们身后的巨幅数字背景板上，山峦环抱、碧波澄澈的北京怀柔雁栖湖 ​展开c",
      "text_raw": "【#第一观察#| 肩负起推进妇女事业发展的共同责任】10月13日上午，北京国家会议中心，在全球妇女峰会现场，新华社记者的镜头定格下珍贵瞬间——峰会开始前，国家主席习近平和夫人彭丽媛同与会各国和国际组织代表团团长夫妇合影留念。他们身后的巨幅数字背景板上，山峦环抱、碧波澄澈的北京怀柔雁栖湖 ​展开c",
      "reposts": 23,
      "comments": 35,
      "likes": 90,
      "pics": [
        "https://tvax4.sinaimg.cn/crop.0.0.750.750.180/0085KfK1ly8h540v278acj30ku0kuzkp.jpg?KID=imgbed,tva&Expires=1761666922&ssig=Nx2VqLlCIy",
        "https://tvax2.sinaimg.cn/crop.58.61.875.875.180/001R0E0aly8h8vg6xx3srj60rs0rsdko02.jpg?KID=imgbed,tva&Expires=1761666924&ssig=6z6EtAKShP",
        "https://h5.sinaimg.cn/upload/108/1866/2022/11/02/vvip_4.png",
        "https://wx2.sinaimg.cn/large/001R0E0aly1i6b3ipcz16j60rs0fmjtf02.jpg",
        "https://h5.sinaimg.cn/upload/2016/12/28/14/feed_headlines_icon_flash20161228_3.png",
        "https://tva1.sinaimg.cn/default/images/default_avatar_male_180.gif",
        "https://a.sinaimg.cn/mintra/pic/2201190827/32aria.png"
      ],
      "video": null,
      "score": 33.3
    },
    {
      "id": "detail-7650380348822664595",
      "bid": null,
      "url": "https://weibo.com/1699432410/Q8GYtzZwt?refer_flag=1001030103_",
      "created_at": "10月12日 00:21",
      "user_id": null,
      "user_name": "新华社",
      "verified": null,
      "region": null,
      "source": "",
      "text": "【#第一观察#|#总书记激励巾帼之花绽放新时代#】在全球妇女峰会即将举行之际，我们重温习近平总书记的重要论述，共同展望妇女发展的美好未来，期待全球妇女事业发展谱写新的绚烂篇章。详情请看↓O第一观察 | 总书记激励巾帼之花绽放新时代​",
      "text_raw": "【#第一观察#|#总书记激励巾帼之花绽放新时代#】在全球妇女峰会即将举行之际，我们重温习近平总书记的重要论述，共同展望妇女发展的美好未来，期待全球妇女事业发展谱写新的绚烂篇章。详情请看↓O第一观察 | 总书记激励巾帼之花绽放新时代​",
      "reposts": 233,
      "comments": 122,
      "likes": 758,
      "pics": [
        "https://tvax4.sinaimg.cn/crop.0.0.750.750.180/0085KfK1ly8h540v278acj30ku0kuzkp.jpg?KID=imgbed,tva&Expires=1761666923&ssig=ONA2TuUREE",
        "https://tvax2.sinaimg.cn/crop.58.61.875.875.180/001R0E0aly8h8vg6xx3srj60rs0rsdko02.jpg?KID=imgbed,tva&Expires=1761666924&ssig=6z6EtAKShP",
        "https://h5.sinaimg.cn/upload/108/1866/2022/11/02/vvip_4.png",
        "https://wx4.sinaimg.cn/large/001R0E0aly1i68w900am7j60qh0ewjum02.jpg",
        "https://tvax2.sinaimg.cn/crop.58.61.875.875.180/001R0E0aly8h8vg6xx3srj60rs0rsdko02.jpg?KID=imgbed,tva&Expires=1761666908&ssig=Fiax9fSI6h",
        "https://h5.sinaimg.cn/upload/2016/12/28/14/feed_headlines_icon_flash20161228_3.png",
        "https://tva1.sinaimg.cn/default/images/default_avatar_male_180.gif",
        "https://a.sinaimg.cn/mintra/pic/2201190827/32aria.png"
      ],
      "video": null,
      "score": 252.2
    },
    {
      "id": "detail-4247115986995693971",
      "bid": null,
      "url": "https://weibo.com/1789594967/Q8KoS93yW?refer_flag=1001030103_",
      "created_at": "10月12日 09:04",
      "user_id": null,
      "user_name": "山西青年报",
      "verified": null,
      "region": null,
      "source": "",
      "text": "【#第一观察#|#总书记激励巾帼之花绽放新时代#】在全球妇女峰会即将举行之际，我们重温习近平总书记的重要论述，共同展望妇女发展的美好未来，期待全球妇女事业发展谱写新的绚烂篇章。详情请看↓  ​​​O第一观察 | 总书记激励巾帼之花绽放新时代​",
      "text_raw": "【#第一观察#|#总书记激励巾帼之花绽放新时代#】在全球妇女峰会即将举行之际，我们重温习近平总书记的重要论述，共同展望妇女发展的美好未来，期待全球妇女事业发展谱写新的绚烂篇章。详情请看↓  ​​​O第一观察 | 总书记激励巾帼之花绽放新时代​",
      "reposts": 2,
      "comments": 0,
      "likes": 6,
      "pics": [
        "https://tvax4.sinaimg.cn/crop.0.0.750.750.180/0085KfK1ly8h540v278acj30ku0kuzkp.jpg?KID=imgbed,tva&Expires=1761666924&ssig=gLedKYWEUa",
        "https://tvax3.sinaimg.cn/crop.0.0.709.709.180/6aab0d57ly8h8vggsx3yfj20jp0jpab8.jpg?KID=imgbed,tva&Expires=1761666925&ssig=g%2FfAK2xQO%2F",
        "https://h5.sinaimg.cn/upload/108/1866/2022/11/02/vip_5.png",
        "https://wx4.sinaimg.cn/large/001R0E0aly1i68w900am7j60qh0ewjum02.jpg",
        "https://tvax2.sinaimg.cn/crop.58.61.875.875.180/001R0E0aly8h8vg6xx3srj60rs0rsdko02.jpg?KID=imgbed,tva&Expires=1761666925&ssig=q9D8%2BZmplc",
        "https://h5.sinaimg.cn/upload/2016/12/28/14/feed_headlines_icon_flash20161228_3.png",
        "https://tva1.sinaimg.cn/default/images/default_avatar_male_180.gif",
        "https://a.sinaimg.cn/mintra/pic/2201190827/32aria.png"
      ],
      "video": null,
      "score": 1.8
    },
    {
      "id": "detail-4968393429703362957",
      "bid": null,
      "url": "https://weibo.com/1699432410/Q71b1FgTt?refer_flag=1001030103_",
      "created_at": "10月01日 00:06",
      "user_id": null,
      "user_name": "新华社",
      "verified": null,
      "region": null,
      "source": "",
      "text": "【#第一观察#| 总书记国庆招待会重要讲话饱含深意】9月30日晚，庆祝中华人民共和国成立76周年招待会在人民大会堂举行，习近平总书记出席招待会并发表重要讲话。总书记重要讲话总结辉煌成就、凝聚奋进力量、展望光明前景，在继往开来的重要时刻凝聚起推进强国建设、民族复兴伟业的强大力量。详情请看↓ ​展开c",
      "text_raw": "【#第一观察#| 总书记国庆招待会重要讲话饱含深意】9月30日晚，庆祝中华人民共和国成立76周年招待会在人民大会堂举行，习近平总书记出席招待会并发表重要讲话。总书记重要讲话总结辉煌成就、凝聚奋进力量、展望光明前景，在继往开来的重要时刻凝聚起推进强国建设、民族复兴伟业的强大力量。详情请看↓ ​展开c",
      "reposts": 76,
      "comments": 48,
      "likes": 373,
      "pics": [
        "https://tvax4.sinaimg.cn/crop.0.0.750.750.180/0085KfK1ly8h540v278acj30ku0kuzkp.jpg?KID=imgbed,tva&Expires=1761666924&ssig=gLedKYWEUa",
        "https://tvax2.sinaimg.cn/crop.58.61.875.875.180/001R0E0aly8h8vg6xx3srj60rs0rsdko02.jpg?KID=imgbed,tva&Expires=1761666925&ssig=q9D8%2BZmplc",
        "https://h5.sinaimg.cn/upload/108/1866/2022/11/02/vvip_4.png",
        "https://wx2.sinaimg.cn/large/001R0E0aly1i5w5t2iqb8j60rs0fmq6f02.jpg",
        "https://tvax2.sinaimg.cn/crop.58.61.875.875.180/001R0E0aly8h8vg6xx3srj60rs0rsdko02.jpg?KID=imgbed,tva&Expires=1761666895&ssig=7Hjscm5JhX",
        "https://h5.sinaimg.cn/upload/2016/12/28/14/feed_headlines_icon_flash20161228_3.png",
        "https://tva1.sinaimg.cn/default/images/default_avatar_male_180.gif",
        "https://a.sinaimg.cn/mintra/pic/2201190827/32aria.png"
      ],
      "video": null,
      "score": 97.30000000000001
    },
    {
      "id": "detail-7464073999349669574",
      "bid": null,
      "url": "https://weibo.com/1699432410/Q6gm72UKz?refer_flag=1001030103_",
      "created_at": "09月26日 00:54",
      "user_id": null,
      "user_name": "新华社",
      "verified": null,
      "region": null,
      "source": "",
      "text": "【#第一观察#·瞬间 | 情满天山 心心相印】祖国的西北角，166万平方公里的大美新疆，天山南北好风光。新疆维吾尔自治区成立70周年之际，9月23日，习近平总书记率中央代表团来到乌鲁木齐，同新疆各族人民共同庆祝盛大的节日。3天时间，所到之处，欢声笑语，情深意长。详情请看↓O第一观察·瞬间 | 情满天山 心心相印​",
      "text_raw": "【#第一观察#·瞬间 | 情满天山 心心相印】祖国的西北角，166万平方公里的大美新疆，天山南北好风光。新疆维吾尔自治区成立70周年之际，9月23日，习近平总书记率中央代表团来到乌鲁木齐，同新疆各族人民共同庆祝盛大的节日。3天时间，所到之处，欢声笑语，情深意长。详情请看↓O第一观察·瞬间 | 情满天山 心心相印​",
      "reposts": 41,
      "comments": 33,
      "likes": 159,
      "pics": [
        "https://tvax4.sinaimg.cn/crop.0.0.750.750.180/0085KfK1ly8h540v278acj30ku0kuzkp.jpg?KID=imgbed,tva&Expires=1761666924&ssig=gLedKYWEUa",
        "https://tvax2.sinaimg.cn/crop.58.61.875.875.180/001R0E0aly8h8vg6xx3srj60rs0rsdko02.jpg?KID=imgbed,tva&Expires=1761666925&ssig=q9D8%2BZmplc",
        "https://h5.sinaimg.cn/upload/108/1866/2022/11/02/vvip_4.png",
        "https://wx4.sinaimg.cn/large/001R0E0aly1i5qf7wyj2rj60rs0fmwhz02.jpg",
        "https://h5.sinaimg.cn/upload/2016/12/28/14/feed_headlines_icon_flash20161228_3.png",
        "https://tva1.sinaimg.cn/default/images/default_avatar_male_180.gif",
        "https://a.sinaimg.cn/mintra/pic/2201190827/32aria.png"
      ],
      "video": null,
      "score": 50.4
    },
    {
      "id": "detail-6942901361206566794",
      "bid": null,
      "url": "https://weibo.com/1699432410/Q6fVXBriE?refer_flag=1001030103_",
      "created_at": "09月25日 23:50",
      "user_id": null,
      "user_name": "新华社",
      "verified": null,
      "region": null,
      "source": "",
      "text": "【#第一观察#| 总书记身体力行推进中华民族共同体建设】9月24日，习近平总书记听取新疆维吾尔自治区党委和政府工作汇报，强调“紧紧围绕铸牢中华民族共同体意识、推进中华民族共同体建设”。详情请看↓O第一观察 | 总书记身体力行推进中华民族共同体建设​",
      "text_raw": "【#第一观察#| 总书记身体力行推进中华民族共同体建设】9月24日，习近平总书记听取新疆维吾尔自治区党委和政府工作汇报，强调“紧紧围绕铸牢中华民族共同体意识、推进中华民族共同体建设”。详情请看↓O第一观察 | 总书记身体力行推进中华民族共同体建设​",
      "reposts": 38,
      "comments": 7,
      "likes": 97,
      "pics": [
        "https://tvax4.sinaimg.cn/crop.0.0.750.750.180/0085KfK1ly8h540v278acj30ku0kuzkp.jpg?KID=imgbed,tva&Expires=1761666924&ssig=gLedKYWEUa",
        "https://tvax2.sinaimg.cn/crop.58.61.875.875.180/001R0E0aly8h8vg6xx3srj60rs0rsdko02.jpg?KID=imgbed,tva&Expires=1761666925&ssig=q9D8%2BZmplc",
        "https://h5.sinaimg.cn/upload/108/1866/2022/11/02/vvip_4.png",
        "https://wx1.sinaimg.cn/large/001R0E0aly1i5qd4vtyodj60rs0fm42002.jpg",
        "https://h5.sinaimg.cn/upload/2016/12/28/14/feed_headlines_icon_flash20161228_3.png",
        "https://tva1.sinaimg.cn/default/images/default_avatar_male_180.gif",
        "https://a.sinaimg.cn/mintra/pic/2201190827/32aria.png"
      ],
      "video": null,
      "score": 34.6
    },
    {
      "id": "detail-6499806310590503569",
      "bid": null,
      "url": "https://weibo.com/1699432410/Q6fXV6Jkq?refer_flag=1001030103_",
      "created_at": "09月25日 23:55",
      "user_id": null,
      "user_name": "新华社",
      "verified": null,
      "region": null,
      "source": "",
      "text": "【#第一观察#｜习近平主席宣布的“中国承诺”彰显负责任大国担当】9月24日，习近平主席在联合国气候变化峰会发表视频致辞时，郑重宣布中国新一轮国家自主贡献。详情请看↓O第一观察｜习近平主席宣布的“中国承诺”彰显负责任大国担当​",
      "text_raw": "【#第一观察#｜习近平主席宣布的“中国承诺”彰显负责任大国担当】9月24日，习近平主席在联合国气候变化峰会发表视频致辞时，郑重宣布中国新一轮国家自主贡献。详情请看↓O第一观察｜习近平主席宣布的“中国承诺”彰显负责任大国担当​",
      "reposts": 27,
      "comments": 7,
      "likes": 78,
      "pics": [
        "https://tvax4.sinaimg.cn/crop.0.0.750.750.180/0085KfK1ly8h540v278acj30ku0kuzkp.jpg?KID=imgbed,tva&Expires=1761666925&ssig=YhB5KnPvhQ",
        "https://tvax2.sinaimg.cn/crop.58.61.875.875.180/001R0E0aly8h8vg6xx3srj60rs0rsdko02.jpg?KID=imgbed,tva&Expires=1761666925&ssig=q9D8%2BZmplc",
        "https://h5.sinaimg.cn/upload/108/1866/2022/11/02/vvip_4.png",
        "https://wx4.sinaimg.cn/large/001R0E0aly1i5qd6n3sfqj60rs0fmwgj02.jpg",
        "https://h5.sinaimg.cn/upload/2016/12/28/14/feed_headlines_icon_flash20161228_3.png",
        "https://tva1.sinaimg.cn/default/images/default_avatar_male_180.gif",
        "https://a.sinaimg.cn/mintra/pic/2201190827/32aria.png"
      ],
      "video": null,
      "score": 26.1
    }
  ]
}